{
  "id": 8547,
  "title": "电光学院团干校强化提升学员“沟通能力”",
  "url": "http://news.nankai.edu.cn/dcxy/system/2016/05/09/000280394.shtml",
  "date": "2016-05-09",
  "source": "来源： 南开新闻网",
  "content": "南开新闻网讯(通讯员 郭宇涵 霍丽敏)4月24日，电光学院团干校邀请到生命科学学院党委秘书王兰，为团干校学员作题为“沟通能力提升”的专题讲座。学院团委老师朱博晨出席。\n王兰从“沟通在工作学习生活中的重要作用”入手，着重讲述了语言和情绪对沟通的影响，细致分析了语言交流中可能存在的障碍，并针对这些问题提出了相应的解决措施。讲座过程中，王兰借助视频、PPT等多种形式，与学员们互动，形象描述了非语言信息在沟通中的作用。学员们积极响应，现场气氛活跃。\n学员王沛曌表示，“今天的讲座让我明白了沟通是有魔力的，良好的沟通会取得事半功倍的效果，提升沟通能力对于每个人都是非常重要的。”\n讲座结束后，团干校负责人对下一阶段各小组的专题活动策划进行了专项布置。\n据悉，电光学院第三期团干校已持续开展了4期专题讲座，分别从理论修养、学生工作能力、沟通表达等方面对学员进行指导和训练。",
  "content_length": 382,
  "snapshot_hash": "2dc47bd8aeebd0c16f6ab64f82570979",
  "attachments": [],
  "crawl_time": "2025-05-29T03:22:58.448563",
  "list_page_url": "https://news.nankai.edu.cn/dcxy/system/count//0005000/000000000000/000/000/c0005000000000000000_000000284.shtml"
}