{
  "id": 4182,
  "title": "【社会实践】“公能薪火”实践队广州考察",
  "url": "http://news.nankai.edu.cn/dcxy/system/2012/07/21/000078955.shtml",
  "date": "2012-07-21",
  "source": "来源： 南开新闻网",
  "content": "南开新闻网讯(通讯员 陈超)7月19日，南开大学历史学院“公能薪火”实践队在主楼总理像前举行了简短的出征仪式，开始了为期5天以“薪火相传九十载，南国青春耀华夏”为主题的实践活动。“公能薪火”实践队是今年学校重点暑期实践队之一，实践团队由《南开青年》报社以及历史学院主要学生干部组成，由历史学院近现代史方面教师李少兵担任指导教师，校团委和历史学院团委相关负责老师担任领队。\n活动将在广州及其周边地区开展，围绕中国社会主义青年团第一次全国代表大会、中国共产党第三次全国代表大会等具有重大历史意义的事件，通过一系列的实地考察、学术交流活动，追溯中国共产党早期革命之路与中国共青团的建立。实践队在组建之初，即考虑到了当地良好的资源，并结合今年这样一个特殊时机——各地青年共庆中国共青团成立九十周年，全国人民喜迎中国共产党第十八次全国代表大会。通过对中国革命史和中国共青团团史的实地调研，做到回顾历史，总结历史，学习历史，为未来提供借鉴与指导。\n广东地区在中国近现代史尤其是中国革命史上具有重要的地位，中国青年革命运动与早期中国革命在此酝酿成熟并壮大。二十世纪以来，广东地区保留了众多革命遗存，如广州起义烈士陵园、黄花岗七十二烈士陵园、中国社会主义青年团一大会址、中共三大会址纪念馆、国民党一大会址等，并以此为依托，建立众多爱国主义教育基地，在对当代青年的思想教育中发挥了至关重要的作用。\n1922年5月5日至5月10日，中国社会主义青年团第一次全国代表大会在广州召开，大会宣告中国社会主义青年团正式成立，成为中国青年运动发展史上的一个里程碑。团的一大会址已建设成为纪念广场和史迹展，于2012年5月8日正式落成揭幕。实践队将赴当地进行考察，同时回顾革命历史，接受红色主题教育，重温九十年前党领导下的青年运动，思考当代大学生的历史肩负。\n1923年6月12日至20日，中国共产党在广州举行第三次全国代表大会。实践队力图通过对于党的三大会址的参观及访谈活动，认识中国共产党成立初期的中心任务。实践队以广州为目的地的原因之一，就是要身临革命现场，对于历史事件产生真切认识与深刻的思考。",
  "content_length": 885,
  "snapshot_hash": "6549c49735a05778f2c4acdc98244d2a",
  "attachments": [],
  "crawl_time": "2025-05-29T02:00:12.045864",
  "list_page_url": "https://news.nankai.edu.cn/dcxy/system/count//0005000/000000000000/000/000/c0005000000000000000_000000139.shtml"
}