{
  "id": 3194,
  "title": "化学学院师生畅谈五四精神与当代青年发展",
  "url": "http://news.nankai.edu.cn/dcxy/system/2011/05/05/000038873.shtml",
  "date": "2011-05-05",
  "source": "来源： 南开新闻网",
  "content": "南开新闻网 (通讯员 张更辉)5月4日中午，化学学院团委、研究生团总支举行了主题为“五四精神与当代青年发展”的座谈会。院党委副书记兼副院长牛文利，团委副书记、研究生团总支书记张更辉与各团支部书记、院研究生会成员共度五四青年节。\n座谈中，大家共同观看了胡锦涛总书记在庆祝清华大学建校100周年庆祝大会上的讲话视频，集体学习了温家宝总理“五四”前夕同首都各界青年代表座谈时的谈话精神。随后，大家一起就五四精神和当代青年发展进行了热烈讨论。院团委研究生副书记刘珊珊带领大家对“五四精神”进行了回顾，五四精神的内涵“爱国、进步、民主、科学”所体现的是青年人勇担重担的精神风貌，当代青年同样要肩负起新时代的历史使命，在社会发展中主动呈现青年人的智慧和热情，为社会主义现代化建设增砖添瓦。\n院研究生会主席郭磊表示当前青年大学生关注的不应只有学业发展，还有未来的职业规划。近期研究生会组织的南开大学首届研究生模拟招聘大赛吸引了全校学生的关注，证明了当代大学生已经不仅仅只关注象牙塔里的学习，对社会实践和职业发展也十分重视。\n院团委办公室主任李海霞表示在胡锦涛总书记的讲话中，关于创新的要求给了自己很深的印象。在科学试验中，大家勇于创新，其实在团学工作中同样要注重创新。尽管研究生科研任务繁重，但只要能提供好的锻炼平台，能结合青年人的发展需求，大家同样会积极关注和参与。\n最后，牛文利对团委学生干部致以节日的问候并表示适逢清华大学百年校庆，胡锦涛总书记在讲话中对青年人的发展提出了新的希望，温家宝总理在“五四”前夕同首都各界青年代表座谈时也提出当代青年要有理想，善学习，讲道德，要自立，勇奋斗。牛文利希望大家通过此次学习讨论，在今后的工作中积极发挥青年人的主动性和创造性，志存高远，脚踏实地，以良好的精神面貌在科研探索和社会实践中不断谱写绚丽的青春乐章。",
  "content_length": 769,
  "snapshot_hash": "9c4b30c8c3572e0e37bbe68180d50673",
  "attachments": [],
  "crawl_time": "2025-05-29T01:41:37.958050",
  "list_page_url": "https://news.nankai.edu.cn/dcxy/system/count//0005000/000000000000/000/000/c0005000000000000000_000000107.shtml"
}