{
  "id": 15531,
  "title": "南开大学博物馆携手历史学院举办第一届南开文物讲解大赛",
  "url": "http://news.nankai.edu.cn/dcxy/system/2024/06/11/030062135.shtml",
  "date": "2024-06-11",
  "source": "来源： 南开大学新闻网",
  "content": "南开新闻网讯（通讯员 刘星熠 张铭悦）为深入挖掘并阐释南开文物的独特价值，传承文物中蕴含的优秀传统文化，6月5日，南开大学博物馆携手南开大学历史学院举办第一届南开文物讲解大赛。本次比赛邀请学院党委副书记、副院长晏京，南开大学博物馆刘阳，考古学与博物馆学系齐广，学院团委研究生辅导员张铭悦4位老师担任评委。\n本次比赛由选手个人展示及评委点评两个环节组成。在个人展示环节，参赛选手各自选择一件南开大学博物馆馆藏文物进行宣讲。来自3个学院的7位选手，围绕各自选取的文物，从器物特点、历史背景、制作工艺、文化底蕴等角度，进行了全方面的讲解。他们以扎实的专业知识、精美制作的演示文稿、流畅优美的语言、饱满真挚的感情，赢得了现场评委的一致高度评价。\n在评委点评环节，刘阳老师、齐广老师肯定了各位同学的精心准备。他们对每位选手展示中的优点与不足逐一点评，进一步向大家介绍了各件文物的历史背景与文化意蕴，并就展示中讲解词、演示文稿、图片素材、背景音乐等各方面给予针对性建议。两位老师关于“如何讲好一个故事”的建议，给予在场各位选手观众启发。\n各位选手展示结束后，经过得分汇总，本次比赛共评选出一、二、三等奖共计7名，其中陶灼同学荣获一等奖，张瀚月同学、董昊楠同学荣获二等奖，张静心依同学、江雨霏同学、刘端宁同学、陈佳洋同学荣获三等奖。",
  "content_length": 559,
  "snapshot_hash": "4b187783514662c4c9afc6a672bcddd6",
  "attachments": [],
  "crawl_time": "2025-05-29T05:15:51.286572",
  "list_page_url": "https://news.nankai.edu.cn/dcxy/system/count//0005000/000000000000/000/000/c0005000000000000000_000000516.shtml"
}