{
  "id": 14810,
  "title": "医学院实践队开展“打破偏见，融爱唐心”扶助唐氏综合征活动",
  "url": "http://news.nankai.edu.cn/dcxy/system/2023/07/20/030057158.shtml",
  "date": "2023-07-20",
  "source": "来源： 南开大学新闻网",
  "content": "南开新闻网讯 （通讯员 林显京） 为促进残疾人事业高质量发展，增强大学生对心智障碍者的认同与接受，医学院“融爱唐心”实践队走进唐氏综合征等心智障碍社会帮扶机构，通过与专业人士共同设计科学活动，与患者及家庭友好互动，为残疾人帮扶提出合理建议。\n实践队首先前往天津市中心妇产医院，进行唐氏综合征相关筛查诊断技术的学习调研。通过医生的深入讲解，队员们学习了唐氏综合征的预防、诊断及治疗等相关知识，了解了无创DNA产前筛查技术的临床优势、试用目标和应用定位，并围绕产前诊断的普及性、政策补助与宣传等进行了讨论交流。\n为了将理论知识更好应用于实际，实践队先后前往北京融爱融乐心智障碍者家庭支持中心、长沙唐果之家唐氏综合征互助中心，深入了解其组织机构、服务内容和社会作用，并积极投身融合志愿服务。在专业教师的指导下，志愿者和心智障碍伙伴结成一对一的陪伴关系，通过舞蹈学习、形体练习和非洲鼓表演，辅助孩子们集中注意力完成动作，增进了与心智障碍伙伴的关系，提升了他们的自尊心和社交技能。\n实践过程中，队员们不断思考各类帮扶模式对唐氏综合征患儿的支持作用，探讨如何为唐氏综合征患者提供更好的医疗照顾与社会支持，并帮助患者重返社会。队员们表示：“我们希望提高大家对唐氏综合症的认识和理解，创造一个包容和融洽的环境，让更多人认识到唐氏综合症患者的能力和潜力，为唐氏综合症患者提供关爱和支持。”",
  "content_length": 585,
  "snapshot_hash": "26bfa86878e8040f4aeabafacb1f7bb8",
  "attachments": [],
  "crawl_time": "2025-05-29T05:05:45.303052",
  "list_page_url": "https://news.nankai.edu.cn/dcxy/system/count//0005000/000000000000/000/000/c0005000000000000000_000000495.shtml"
}