{
  "id": 6434,
  "title": "化学学院“青春赞歌班班唱”比赛举行",
  "url": "http://news.nankai.edu.cn/dcxy/system/2014/03/24/000171017.shtml",
  "date": "2014-03-24",
  "source": "来源： 南开新闻网",
  "content": "南开新闻网讯(通讯员 马婧 张更辉)3月23日，化学学院“青春赞歌班班唱”比赛举行，正式拉开了学院参评”五月的鲜花”合唱比赛的序幕。\n开学以来，按照校团委的部署要求，化学学院团委在第一时间指定专人负责“班班唱”活动，精心制作了策划方案，学院各班级同学积极参与其中。“他们或在体育场，或在化学楼前，或在宿舍楼下，精心排练，参与热情大大出乎了我们的预料。”负责活动的同学说。\n院内评比的舞台上，各班同学们充分展现了他们对于合唱的热情和集体的智慧，演出形式别出心裁，演出风格各有不同。\n2013级分子一班《同桌的你》让大家回忆起从入学到现在的点点滴滴，每一个微笑，每一个鼓励，那个陪伴左右同桌的你，温馨而感怀；之后材料一班的一首《送别》，同学们自编自导的舞台剧情，让这首悠扬的歌区，在这充满留恋情愫的毕业季，更显动情。化学一班的合唱改编了流行歌曲并填入了同学们自己写的歌词，熟练的吉他伴奏引出了同学们演唱的《那些花儿》，而紧接着的《老师考哪儿》改编自热播主题曲“爸爸去哪儿”。而最后一首《桃花源》主要由男生合唱，富有青春热情的演唱令同学们大呼过瘾。\n经评委考评，2013级化学一班夺得化学学院“青春赞歌班班唱”一等奖，化学二班、四班、伯苓班、三班、五班等分别获得二三等奖。\n“青春赞歌班班唱”活动中，各班班服、班旗、班级口号纷纷亮相，参与学生的范围更大，合唱的热情更高，班级凝聚力和荣誉感也在合唱中得到了升华。此后，获奖班级的同学将代表学院参加我校“五月的鲜花”合唱比赛。",
  "content_length": 633,
  "snapshot_hash": "ff159be8aa816e7c0cc855bf78a28f7a",
  "attachments": [],
  "crawl_time": "2025-05-29T02:43:10.823733",
  "list_page_url": "https://news.nankai.edu.cn/dcxy/system/count//0005000/000000000000/000/000/c0005000000000000000_000000213.shtml"
}