{
  "id": 5065,
  "title": "经济学院青志协举办世界地球日活动",
  "url": "http://news.nankai.edu.cn/dcxy/system/2013/04/26/000120695.shtml",
  "date": "2013-04-26",
  "source": "来源： 南开新闻网",
  "content": "南开新闻网讯(通讯员 袁芳 王梦蛟)4月22日，随着世界地球日的到来，经济学院青年志愿者协会“世界地球日·关注H7N9”健康知识有奖问答活动在校本部二食堂前火热进行。活动旨在通过传单、手工展板、有奖竞答等多种方式号召南开学子关注预防H7N9，加大对地球生态问题的重视与关注。\n活动中，经院青志协同学用宣传单和展板介绍了H7N9病毒且分条列出预防措施。有奖竞答的奖品为医用口罩和硫磺皂，实用而有意义，帮助南开学子预防流感、守住健康。活动得到了众多过往学生的肯定与支持。\n世界地球日(World Earth Day)在每年的4月22日，是一项世界性的环境保护活动。该活动最初在1970年由美国人盖洛德·尼尔森和丹尼斯·海斯发起，旨在唤起人类爱护地球、保护家园的意识，促进资源开发与环境保护的协调发展，进而改善地球的整体环境。中国从20世纪90年代起，开始参与到活动的组织中来。南开大学经济学院青年志愿者协会每年会在地球日这一天开展丰富而有意义的环保倡议活动。",
  "content_length": 427,
  "snapshot_hash": "72f9353a40330d412f60d68a885022b0",
  "attachments": [],
  "crawl_time": "2025-05-29T02:16:47.152775",
  "list_page_url": "https://news.nankai.edu.cn/dcxy/system/count//0005000/000000000000/000/000/c0005000000000000000_000000168.shtml"
}