{
  "id": 3346,
  "title": "商学有约：青年校友分享学术前沿及留学经历",
  "url": "http://news.nankai.edu.cn/dcxy/system/2011/06/09/000039640.shtml",
  "date": "2011-06-09",
  "source": "来源： 南开新闻网",
  "content": "南开新闻网讯(通讯员 周轩)6月7日，“商学有约”暨青年校友沙龙举办学术前沿及留学经历分享沙龙。\n主讲嘉宾梁昊现为荷兰蒂尔堡大学经济研究中心金融学研究型硕士生，南开大学商学院工商管理本科毕业。在荷兰就读硕士期间，梁昊完成的数篇金融、战略、经济方向的英文论文，被美国哈佛大学、丹麦哥本哈根商学院、德国Otto Beisheim School of Management、伦敦政治经济学院、爱尔兰都柏林大学、意大利威尼斯国际大学、北京大学、清华大学等顶尖学府邀请并与名校教授博士们同台演讲，部分论文已经发表在国外高质量的英文期刊上。\n梁昊与大家分享的学术前沿题目为“从制度到脑神经”，内容涵盖了他目前在做的一系列研究内容，包括从制度理论的视角探讨国家与制度如何影响中国企业在海外投资、并购、吸引私募股权融资、公司治理与高管薪酬等方面的决策，以及金融市场中投资者行为与市场机制设计等。此外，讲座简要介绍目前金融前沿领域的实验与脑神经金融学研究成果，以及其与制度和行为的联系。\n本次沙龙吸引了商学院林润辉、任兵、田莉、任星耀等多位老师和众多博士、硕士研究生和高年级本科生的参与。他们就梁昊同学的学术报告开展了热烈的交流和讨论。南开管理学术沙龙创建者任兵老师主持了本次沙龙活动。林润辉高度评价了梁昊同学的研究成果，提出了自己中肯的指导意见，并希望能有更多的同学通过国际交流走上国际化发展道路。来自《南开管理评论》的田莉向梁昊约稿，希望能有更多的海外校友支持刊物海外版的发展。\n学术分享结束后，梁昊还与参加沙龙的同学们分享了自己在海外留学的经历和心得。梁昊拥有丰富的留学经历，本科曾在新加坡管理大学交换学习一年，在康奈尔大学学习半年，目前享有蒂尔堡大学研究生院最高奖学金，以及荷兰政府硕士最高奖学金Huygens Programme的资助。准备出国的高年级本科同学们围绕自己感兴趣的留学问题，与梁昊进行了深入的探讨。\n本次商学有约暨青年校友沙龙活动由商学院学生工作办公室主办，得到了南开管理学术沙龙的大力支持。",
  "content_length": 849,
  "snapshot_hash": "c034f6480877184ef355a393086a563b",
  "attachments": [],
  "crawl_time": "2025-05-29T01:44:58.333128",
  "list_page_url": "https://news.nankai.edu.cn/dcxy/system/count//0005000/000000000000/000/000/c0005000000000000000_000000112.shtml"
}