{
  "id": 9916,
  "title": "【关注十九大】马克思主义学院举办“十九大光辉旗帜新时代扬...",
  "url": "http://news.nankai.edu.cn/dcxy/system/2017/10/30/000353015.shtml",
  "date": "2017-10-30",
  "source": "来源： 南开新闻网",
  "content": "南开新闻网讯(通讯员 王煜)10月27日，马克思主义学院举办“十九大光辉旗帜新时代扬帆远航”主题文化宣传月活动。院学生会邀请到学院肖光文副教授做开幕主讲，以“引领复兴路，开启新征程--党的十九大报告的精神解读与思考”为主题，为学生解读党的十九大精神。历史学院、哲学院、周恩来政府管理学院、金融学院、旅游与服务学院、电子信息与光学工程学院、环境科学与工程学院、药学院和马克思主义学院等9个学院的150余名学生参加了学习，学院团委书记陈永刚参加了活动。会议由学生会骨干靳斯琪主持。\n会上，肖光文分别从大会报告的主题、报告的“八个新”、报告的重大意义、青春梦激扬中国梦等四个方面深度解读了党的十九大精神。\n他讲道，大会主题昭示了举什么旗，走什么路，以什么样的精神状态，担负什么样的历史使命，实现什么样的奋斗目标。他谈到，中国共产党人的初心和使命就是为中国人民谋幸福，为中华民族谋复兴，这个初心和使命是激励中国共产党人不断前进的根本动力。他从党的十二大讲到党的十九大，进一步解释了中国特色社会主义的形成和发展。从“两个一百年”奋斗目标、决胜全面建成小康社会、新时代中国特色社会主义和中国梦等方面对大会主题做了深入解读。\n肖光文把大会报告归纳为“八个新”，新变革、新时代、新矛盾、新目标、新使命、新思想、新方略和新征程。他从历史维度、主义维度和世界维度等三个方面解读了“新时代”，从“中国梦”、“两个一百年”、“四个伟大”等角度解读了“新使命”。他还特别指出，理论创新至关重要，习近平新时代中国特色社会主义思想开辟了马克思主义新境界，开辟了中国特色社会主义新境界，开辟了治国理政新境界，开辟了管党治党新境界。\n会上，肖光文从政治意义、理论意义和实践意义三个方面对大会报告的重大意义进行了解读。他鼓励同学们将自己的青春梦融入到中国梦当中，秉承南开“知中国而服务中国”的优良传统，用自身实践开启中国特色社会主义伟大新征程。他以深厚的理论底蕴、丰富的实际案例、幽默的言语表达，赢得了全场阵阵掌声。\n听完讲座，学生代表分别从党的十八大以来家乡的新变化新发展、理论创新、生态文明建设、经济发展等方面就学习党的十九大精神谈了自己的感受。\n随后，学院学文部部长何昭宇同学带领同学们发起倡言，“南开学生要认真学习领悟党的十九大精神，深入把握习近平新时代中国特色社会主义思想内涵，不忘初心，牢记使命，秉承“公能”精神，在实现社会主义现代化的新征程中砥砺奋进，用青春热血谱写中华民族伟大复兴的新篇章！”\n活动最后，陈永刚对活动进行总结，他谈道，肖光文老师对于十九大报告的精彩解读为同学们带来了一场精神“大餐”，解了“思想”上“渴”。他希望同学们深刻领会党的十九大精神，用实际行动在伟大新征程中留下南开学子“公能”足迹。",
  "content_length": 1144,
  "snapshot_hash": "4ef22d6072cc491ffb6d8b06c130613a",
  "attachments": [],
  "crawl_time": "2025-05-29T03:49:08.593134",
  "list_page_url": "https://news.nankai.edu.cn/dcxy/system/count//0005000/000000000000/000/000/c0005000000000000000_000000332.shtml"
}