{
  "id": 5857,
  "title": "“活力南开 精彩儒西”趣味运动会火热进行",
  "url": "http://news.nankai.edu.cn/dcxy/system/2013/10/24/000148205.shtml",
  "date": "2013-10-24",
  "source": "来源： 南开新闻网",
  "content": "南开新闻网讯(通讯员 崔宇 姜芦洋)10月19日，由党委研究生工作部主办、校研究生会承办的“活力南开精彩儒西”趣味运动会在儒西公寓篮球场举行，本次活动是第五届儒西公寓文化活动月系列活动之一，旨在增强广大研究生的强身健体意识、培育健康和谐的公寓文化，促进不同学院间研究生的沟通与交流。\n趣味运动会设立了团体赛、双人赛和个人赛三类赛制，并在以往活动的基础上，融入了更新颖、更有趣的运动元素，共包括“接毽球”、“螃蟹赛跑”、“摸石头过河”、“托乒乓球”、“跳长绳”、“拔河”六个精彩纷呈，妙趣横生的子项目。同时，为了鼓励广大研究生的积极参与，主办方不仅给比赛优胜者提供了奖品，而且给每一位参与比赛的同学都准备了一份小礼物。通过网上预报名与现场报名，共有89支双人队伍、22支团体队伍以及个人参赛者在内的500余名研究生参与了本次活动。\n“接毽球”比赛拉开了运动会的序幕。女生的毽子踢得准，男生的毽子踢得远，彩色的毽子在运动场上绚烂纷飞，同学们的掌声和喝彩声不断。“托乒乓球”赛跑考验的是参赛个人的速度和细腻；“摸石头过河”考量的是参赛者的足智多谋；“螃蟹赛跑”讲究的是参赛队员两人间的默契合作；“跳长绳”检验的则是10人参赛团队紧张有序的高度配合。\n妙趣横生的比赛项目、奋力拼搏的参赛选手、团结一致的欢乐氛围，吸引了很多现场观看的同学们也纷纷走上如火如荼的比赛场，检录处一时间人头攒动，热闹非凡，而最后进行的拔河比赛更是将运动会的气氛推向高潮，参赛队伍安排战术、排兵布阵、制定口令，大有捍卫领土寸土不让的架势，三轮比赛一轮比一轮精彩，指挥声、加油声和欢呼声在赛场回荡。经过一番激烈的角逐，最终周恩来政府管理学院代表队获得冠军。\n据悉，儒西公寓文化活动月已经连续举办了五届，每届以不同的主题，异彩纷呈的活动，帮助新生更快地融入南开氛围，感受南开温暖，让研究生们在这片儒西小天地里留下一段美好愉快的记忆。目前，第五届儒西公寓文化活动月已经启动了生活安全宣传展、趣味运动会等活动，还将陆续推出更多丰富多彩的主题活动，助力南开学子“健康生活，快乐科研”。",
  "content_length": 870,
  "snapshot_hash": "11f059283b362fa93f0bac8186f6fe5c",
  "attachments": [],
  "crawl_time": "2025-05-29T02:32:15.265055",
  "list_page_url": "https://news.nankai.edu.cn/dcxy/system/count//0005000/000000000000/000/000/c0005000000000000000_000000193.shtml"
}