{
  "id": 13729,
  "title": "生科院线上举办电信诈骗案例分析暨校园疫情防控安全主题讲座",
  "url": "http://news.nankai.edu.cn/dcxy/system/2022/04/04/030050803.shtml",
  "date": "2022-04-04",
  "source": "来源： 南开大学新闻网",
  "content": "南开新闻网讯（通讯员 王天皓）3月31日，生命科学学院以线上直播形式举办电信诈骗案例分析暨校园疫情防控安全主题讲座，邀请学府街派出所杜静警官、郑和旭警官进行宣讲。生命科学学院学生工作负责人出席并主持活动，本硕博各年级600余名学生线上参会。\n杜静警官以国家反诈中心发布的《防范电信网络诈骗宣传手册》为基础，充分结合工作实际，从网络贷款诈骗、刷单返利诈骗、“杀猪盘”诈骗等十种常见的电信网络诈骗类型出发，通过一个个真实案件事例，为大家详细拆解分析了电信诈骗的常见犯罪手法，引导大家以发生在身边的受骗事件为警示，提高自身防诈反诈意识和鉴别能力。最后，她提醒广大同学认真使用“国家反诈中心”手机APP，并为大家讲解了该应用下载注册的整体流程和有效使用方式。\n郑和旭警官结合疫情防控规定，为大家讲解了与高校学生息息相关的疫情防控注意事项，通过列举因隔离期间未经报备擅自外出、编造虚假疫情信息、拒不配合防疫人员开展工作、隐瞒真实行程信息等原因而受到处分处罚的实际案例，让同学们对于校园疫情防控安全需要大家共同维护这一观念有了更深刻的认识。他强调，作为成年人，大家应树立起正确的法律观念和底线思维，对自己的所作所为负责，践行好自身作为社会公民的责任与担当。\n两位警官的讲解深入浅出、入脑入心，使同学们提升了有力辨别和防范电信诈骗、有效保护自身生命财产安全、有序践行校园疫情防控规定的主动意识和行动自觉，同学们纷纷表示受益匪浅、倍感警醒。\n会后，学院学生工作负责人提醒同学们牢记两位警官讲解的注意事项，擦亮眼睛、提高警惕，不让骗子有机可乘；杜绝侥幸心理，遵守学校疫情防控的各项管理规定，积极配合学校完成日常排查、核酸检测等防疫工作。希望大家自觉成为校园安全的维护者、防诈反诈的践行者、安全观念的宣传者，以身体力行的实际行动和严以律己的主动担当，共同筑牢校园安全防线。",
  "content_length": 776,
  "snapshot_hash": "661971dd45566a61395b87237b300e91",
  "attachments": [],
  "crawl_time": "2025-05-29T04:49:46.595553",
  "list_page_url": "https://news.nankai.edu.cn/dcxy/system/count//0005000/000000000000/000/000/c0005000000000000000_000000458.shtml"
}