{
  "id": 14658,
  "title": "泰达学院、软件学院受邀在滨海新区“以青春之名 在奋进中闪光...",
  "url": "http://news.nankai.edu.cn/dcxy/system/2023/05/09/030056013.shtml",
  "date": "2023-05-09",
  "source": "来源： 南开大学新闻网",
  "content": "南开新闻网讯（通讯员 何骋昊 摄影 何骋昊）为深入学习贯彻党的二十大精神和习近平总书记关于青年工作的重要思想，教育引导广大青年学生厚植爱党爱国爱家乡的情感，展现南开青年积极投身天津“十项行动”的蓬勃力量，丰富同学们的校园生活，以五四青年节为契机，南开大学泰达学院、软件学院积极组织师生参加滨海新区“以青春之名 在奋进中闪光”主题团日活动。\n活动中，南开学子用精心准备的话剧节目《史记—Parastor传》为广大观众演绎了当代青年科研团体在面对国外技术封锁时不屈不挠，迎难而上，最终突破封锁线，研发出国际知名产品的故事，诠释了新时代广大青年踔厉奋发新时代、挺膺担当新征程的信心与担当以及奋发进取的精神风貌，展现出南开学子立大志、明大德、成大才、担大任的勇气和决心。\n学校团委副书记东俊艳、南开大学就业指导中心主任李军、南开大学泰达学院党委副书记王渤洋受邀参加此次活动。\n此次活动也同时加强了学校团委、学校就业指导中心、泰达学院、软件学院与滨海新区的联系与互动，进一步发挥南开大学泰达校区在服务滨城发展的桥梁纽带作用，促进校地、校企深入合作，共同为滨海新区经济社会高质量发展建设作出新的贡献。",
  "content_length": 494,
  "snapshot_hash": "cbcc76e285e1005c6e87fcada22a4f79",
  "attachments": [],
  "crawl_time": "2025-05-29T05:03:07.599799",
  "list_page_url": "https://news.nankai.edu.cn/dcxy/system/count//0005000/000000000000/000/000/c0005000000000000000_000000488.shtml"
}