{
  "id": 4886,
  "title": "信息学院学生党校第九期申请人培训班结业",
  "url": "http://news.nankai.edu.cn/dcxy/system/2013/04/01/000116155.shtml",
  "date": "2013-04-01",
  "source": "来源： 南开新闻网",
  "content": "南开新闻网讯(通讯员 宣信)信息学院党委学生党校第九期申请人培训班3月31日举行最后一次集中学习，信息学院学生工作办公室主任刘一博为本期学员主讲《中国道路的历史渊源与现实基础——兼谈树立中国特色社会主义自信》的讲座。\n刘一博在讲座中结合习近平同志在十二届全国人大一次会议闭幕式上讲话中提到，实现中国梦必须走中国道路、必须弘扬中国精神和必须凝聚中国力量的论述，从中国道路的历史渊源与现实基础入手为党校学员进行解读。他认为中国道路的历史渊源从新中国特别是改革开放的历史性成就、近代以来中国共产党带领人民的艰苦斗争中来，更重要的是从中华文明五千年来的发展逻辑中来。他认为中国道路的现实基础一是中国取得的历史性成就所带来广泛认同，二是与其他国家的历史和现实比较，三是中国道路顺应世界发展的时代潮流，是中华民族贡献给世界的宝贵财富。他殷切希望入党申请人深刻理解并认同中国道路，树立中国特色社会主义自信，以正确的历史观和历史价值观，在“空谈误国、实干兴邦”的理念下励志修身，秉承公能精神，以实际行动为“中国梦”做出贡献。\n会上，学生党校负责同学还就本期培训的作业提交和最终考核做了说明。\n据学生党校负责人介绍，第九期申请人培训班以深入学习宣传党的十八大精神为主要教学内容，共安排了四次集体学习。前三次集中学习分别为马克思主义教育学院院长纪亚光教授主讲的《“中国梦”纵横谈》、经济学院团委书记刘振主讲的《中国特色社会主义的道与路》和刘一博主讲的《毛泽东选集第一卷导读》。“我们深刻地认识到，只有从理论上、历史上搞清楚中国特色社会主义，才能真正坚定中国特色社会主义的道路、理论和制度自信，才能在实现‘中国梦’的征途上踏实地努力，努力争做优秀的青年共产党员。”学生党校校长武淑艳如是说。\n据悉，信息学院党委学生党校将利用随后开启的第七期理论研修班为平台，深入开展“读经典·品原著·共筑中国梦”活动，组织开展研读《毛泽东选集》和中国特色社会主义相关问题的专题理论研讨。",
  "content_length": 824,
  "snapshot_hash": "13a4fbdb84984e1bf5b13bb99a264932",
  "attachments": [],
  "crawl_time": "2025-05-29T02:13:56.425088",
  "list_page_url": "https://news.nankai.edu.cn/dcxy/system/count//0005000/000000000000/000/000/c0005000000000000000_000000162.shtml"
}