{
  "id": 171,
  "title": "法律援助小组走入社区、工地",
  "url": "http://news.nankai.edu.cn/dcxy/system/2006/11/21/000002842.shtml",
  "date": "2006-11-21",
  "source": "来源： 南开新闻网",
  "content": "南开新闻网讯(通讯员 张维平 于洋)11月19日，南开大学法律援助小组在南开区集园道集园里社区面向进城务工人员进行普法宣传活动，为他们提供法律援助，以期增强其法律意识，让他们能够通过法律手段维护自己的正当权益。\n本次法援活动设有工伤处理、劳动工资、工作时间、社会保障等8个咨询台，涉及到进城务工人员的工作、薪酬、生活、保障等各个方面，实用且周全。同学们运用自己在课堂上的所学尽自己最大努力为社区居民答疑解惑。\n咨询活动结束后，同学们来到西横堤中铁四局工地，向当地的进城务工人员赠送了《农民工维权手册》以及牙刷、香皂等生活用品，并代表法学院的同学向投身于天津城市建设第一战线上的工人师傅表示深深的谢意。工作人员对同学们的到来和帮助表示欢迎和感谢，认为自己在外打工，能够通过一些基本的法律常识保护自己的合法权益是非常有用且必要的。\n通过此次活动，同学们不仅将课堂所学融于实践，更是通过与社会上处于基层地位的广大建设者的接触了解了社会，认识了社会，增加了同学学习法学、运用法学、热爱法学的积极性。新生同学纷纷表示，今后会将这项工作深入下去，争取通过自己的工作让更多的人能够运用法律的手段保护自己。",
  "content_length": 495,
  "snapshot_hash": "7acd356e5f7e5770507266e10dde5164",
  "attachments": [],
  "crawl_time": "2025-05-29T00:42:44.731487",
  "list_page_url": "https://news.nankai.edu.cn/dcxy/system/count//0005000/000000000000/000/000/c0005000000000000000_000000004.shtml"
}