{
  "id": 9145,
  "title": "研究生学术周末聚焦外语教师创新发展",
  "url": "http://news.nankai.edu.cn/dcxy/system/2016/11/18/000306175.shtml",
  "date": "2016-11-18",
  "source": "来源： 南开新闻网",
  "content": "南开新闻网讯(通讯员 刘瑞毅 高梦妍)11月17日，上海交通大学外国语学院副院长彭青龙教授做客研究生学术周末，带来题为“科研项目设计与申报——基于新常态下外语教师创新发展的思考”的主题讲座。\n彭青龙从教师发展困境、科研项目设计以及科研项目申报这3个方面切入，详细深入分析了国内外语教师发展现状，涉及外语教育多元化、教师发展职业化、学科条块化和专业知识化等层面，他倡导从国家、学术共同体、市场3种途径进行教师专业提升。他指出外语教师参加培训的3条路径，表达了对教育国际化前沿多领域、多层次、多角度、多热点话题的密切关注和严谨的专业态度。\n在外语学科创新研究方面，彭青龙结合个人学术生涯，阐述了应予遵循的选题原则以及选题策略，并强调了学者应有的独立品格以及学术洞见。\n彭青龙的讲解与分享不仅促进了外国语学院师生们关于外语教师职业发展的认识，同时在相关课题的选择和研究上也给与会人员带来了诸多启示，进一步拓宽了师生们的学术视野。\n彭青龙是外国文学领域知名专家，主要从事商务英语、澳大利亚文学和应用语言学研究。",
  "content_length": 451,
  "snapshot_hash": "dc6c347c20a3da405d00f353426191f1",
  "attachments": [],
  "crawl_time": "2025-05-29T03:34:30.993018",
  "list_page_url": "https://news.nankai.edu.cn/dcxy/system/count//0005000/000000000000/000/000/c0005000000000000000_000000303.shtml"
}