{
  "id": 4362,
  "title": "经济学院召开第十二届中国经济青年学者论坛志愿者培训暨誓师大会",
  "url": "http://news.nankai.edu.cn/dcxy/system/2012/09/21/000088395.shtml",
  "date": "2012-09-22",
  "source": "来源： 南开新闻网",
  "content": "南开新闻网讯(通讯员 袁埜 兰昊)9月19日，距离第十二届中国经济青年学者论坛开幕4天之际，经济学院学生志愿者上岗培训暨誓师大会在经济学院园阶举行。经济学院团委负责同志、经济学院志愿者督导教师、75名志愿者和部分专业教师参加了会议。\n经济学院团委副书记兰昊首先对大家的志愿奉献精神表示肯定，在组织工作中对志愿者进行了分工并对各个岗位的工作内容和目标提出了具体希望和要求。经济学院团委书记刘振根据不同志愿者服务工作的特点进行了针对性强的礼仪培训，风趣生动的培训过程博得志愿者们的阵阵掌声。随后，学院专职教师和行政教师分别从会议人员接待、后勤保障等方面对前期筹备工作进行了通报，对服务期间的注意事项进行了明确。此次志愿者上岗培训大会标志着经济学院志愿者正式投入中国经济青年学者论坛的筹备之中，在志愿付出和悉心工作的同时展现南开学子服务论坛，添彩经院，光荣母校的热情和决心。\n会后，学院负责人表示，希望志愿者们要立足实岗、团结一致、满怀信心地完成本次志愿服务工作，将这次志愿活动作为践行“知行合一”，践行“公能”精神的大好机会。在志愿服务的同时，培养为公之心，学习耐苦之能、团结之能、实践之能，希望南开精神、南开志愿者精神在每个人的心里扎根、成长。\n第十二届中国经济青年学者论坛将于本月22日拉开帷幕，来自全国各地三十余所高校的经济学领域青年才俊将齐聚南开，届时，经济学院的志愿者工作必将成为论坛中一道靓丽的风景。",
  "content_length": 604,
  "snapshot_hash": "107383b785809b86588130f11661adb5",
  "attachments": [],
  "crawl_time": "2025-05-29T02:03:40.076738",
  "list_page_url": "https://news.nankai.edu.cn/dcxy/system/count//0005000/000000000000/000/000/c0005000000000000000_000000143.shtml"
}