{
  "id": 8506,
  "title": "汉语言文化学院留学生走进王朝公司国际学生实践基地",
  "url": "http://news.nankai.edu.cn/dcxy/system/2016/04/30/000279517.shtml",
  "date": "2016-04-30",
  "source": "来源： 南开新闻网",
  "content": "南开新闻网讯(通讯员 陆瑶)4月29日，汉语言文化学院二十余位留学生来到天津王朝酒业，进行文化实践活动。\n留学生在解说员的带领下，先后参观了葡萄酒灌装车间、地下酒窖和宏伟的王朝御苑酒堡。在参观过程中，留学生了解到王朝酒业的发展、葡萄酒在中国的历史，以及葡萄酒的酿制过程，并跟随品酒师学习如何品酒、鉴酒。留学生们被酒堡的欧式建筑风格、基地展品中蕴藏的历史故事、酒堡内的大量藏酒所深深吸引，更有法国留学生和王朝公司的工作人员交流了对葡萄酒的认识。这里的每一个雕塑每一幅画都在描述着葡萄酒的传说，讲述着葡萄酒的历史。参观结束时，留学生们都觉得意犹未尽。\n留学生们表示，此次活动，不但感受到了葡萄酒文化，而且还深刻地体会到中国酒业在三十余年的时间里不断追求卓越的发展历程。\n据悉，多年来，汉语言文化学院一直致力于留学生教学实践活动的开展，仅王朝公司已累计接待了中外学生近千人。这些活动在丰富了留学生课外生活的同时，也为他们了解中国，感受中国文化提供了全新的平台。",
  "content_length": 427,
  "snapshot_hash": "8ea917b659652d1f960e27edf836682b",
  "attachments": [],
  "crawl_time": "2025-05-29T03:22:22.353883",
  "list_page_url": "https://news.nankai.edu.cn/dcxy/system/count//0005000/000000000000/000/000/c0005000000000000000_000000283.shtml"
}