{
  "id": 5644,
  "title": "生命科学学院举办“我的人生我做主”主题讲座",
  "url": "http://news.nankai.edu.cn/dcxy/system/2013/09/25/000141994.shtml",
  "date": "2013-09-25",
  "source": "来源： 南开新闻网",
  "content": "南开新闻网讯（学生记者 赵慧文）9月25日晚，生命科学学院公能宣讲团在第四教学楼举办“我的人生我做主”主题讲座。曾任天津市学生联合会主席，现为生科院动物学专业直博博一学生的张佳庆，与该院大一新生分享了自己本科四年学习生活中的思考与经验。\n主讲人张佳庆在南开学生自制电影《新开之夏》的片段展映后登台，他在影片里客串了一个大一新生，对学生会工作发表了诸多的质疑和自己的见解。张佳庆笑称自己是“有文艺情怀的普通青年”，在奋斗学生工作和学习之余，也爱尝试写作，出演话剧、电影等新鲜挑战。\n热闹的开场介绍迅速拉近了张佳庆与现场学生的距离，随后，他从四个方面阐述了自己四年学习工作中的经验。张佳庆认为，成功的开端是要树立明确的目标，面对人生道路上不断到来的多种可能，做到知己知彼，慎重选择。做出选择后，便要无悔玩命地拼搏。他以自身为例，讲述了自己从刚进大学就立志成为班长和校学生会主席，直到最后将所在班级带成天津市先进班集体，并成功当选天津市学生联合会主席的经历。他认为，这一路脚踏实地的奋斗过程中，正是不断的积淀为自己创造了尽可能多的机会。只有让自己的实力足够强大，才能真正把人生道路掌握在自己手里。\n本次讲座是生命科学学院公能宣讲团面向新生举办的第一次讲座，日后将会有一系列这样的互动交流，贯彻宣讲团“立公增能宣至善，生生不息讲传承”的主旨。",
  "content_length": 567,
  "snapshot_hash": "49f17509da1d27fee2087af616a8801d",
  "attachments": [],
  "crawl_time": "2025-05-29T02:27:50.304262",
  "list_page_url": "https://news.nankai.edu.cn/dcxy/system/count//0005000/000000000000/000/000/c0005000000000000000_000000188.shtml"
}