{
  "id": 15151,
  "title": "新任学生党支部书记研修班开展“学习贯彻习近平文化思想”专...",
  "url": "http://news.nankai.edu.cn/dcxy/system/2023/11/25/030059005.shtml",
  "date": "2023-11-25",
  "source": "来源： 南开大学新闻网",
  "content": "南开新闻网讯（通讯员 徐子尧 郑香燕 冯传芮）11月23日，南开大学2023年新任学生党支部书记研修班开展理论学习讲座，邀请马克思主义学院党委副书记、全国大学生讲思政课公开课一等奖优秀指导教师肖光文教授作题为《不断开创新时代宣传思想文化工作新局面——学习贯彻习近平文化思想和全国宣传思想文化工作会议精神》的主题报告。\n肖光文说，当前我国正面临世界百年未有之大变局，中华民族伟大复兴进入关键时期，推动宣传思想文化工作高质量发展是时代所需、使命所系。他梳理了习近平文化思想的形成过程，指出宣传思想文化工作事关党的前途命运，事关国家长治久安，事关民族凝聚力和向心力，深入学习贯彻习近平文化思想，掌握其科学内涵与实践逻辑是建设高校高质量思政队伍与党务工作队伍的应有之义，为发挥学生党员先锋模范作用提供了有力的思想支撑与方法论指导。\n肖光文论述了习近平文化思想“七个着力”重大要求，强调党员骨干要切实担负起新时代的文化使命，以习近平文化思想武装头脑，在实践中贯彻落实。为此，要坚定文化自信，秉持开放包容，坚持守正创新。要积极把握“时”与“势”，深刻理解习近平文化思想形成的时代背景；认真把握“魂”与“根”，做到“两个结合”；坚定把握“信”与“新”，坚守中华民族的文化主体性，不断推动文化创新创造。\n据悉，本次学习是新任学生党支部书记研修班的必修内容。未来研修班将继续开展系列理论学习讲座，推动学生党员在高校宣传思想文化工作中答好必答题，争当“领头雁”。",
  "content_length": 621,
  "snapshot_hash": "c61127894e5459c04ab2413306ff7c9c",
  "attachments": [],
  "crawl_time": "2025-05-29T05:10:35.643098",
  "list_page_url": "https://news.nankai.edu.cn/dcxy/system/count//0005000/000000000000/000/000/c0005000000000000000_000000503.shtml"
}