{
  "id": 14721,
  "title": "生科院举办第二届“话谈百年 剧演生科”学生话剧节",
  "url": "http://news.nankai.edu.cn/dcxy/system/2023/06/01/030056553.shtml",
  "date": "2023-06-01",
  "source": "来源： 南开大学新闻网",
  "content": "南开新闻网讯（通讯员 刘金洋 李鹏琳）为深入学习贯彻习近平新时代中国特色社会主义思想，迎接生物学科百年，加强2023届毕业生党员教育，5月27日下午，生科院党校在东方艺术大楼举办第二届“话谈百年，剧演生科”学生话剧节。学院党委副书记、副院长王兰出席本次活动，毕业生党员和党校学员共200余人参加活动。\n同学们精心设计排演，经过将近一个月的准备，共8个话剧在此次话剧节中演出。毕业生党员带来话剧《萧采瑜》，一幕幕场景再现了生物学科先贤萧采瑜先生为新中国生物学科发展和教育事业秉公尽能的一生，向老一辈科研工作者致敬；本科生党支部创作的话剧《采莲南塘秋》生动形象地呈现出南开生物的化身——“南生莲”走过的波澜壮阔的百年；《闪闪的红星》由党校学员创新编排，精彩的表演引得观众掌声阵阵，生动演绎出了潘冬子从一个一心只为“复仇”的普通农家少年成长为一名坚定的革命战士的故事；党校学员带来话剧《何为青年，青年何为》为大家再现了百年前中国青年积极向上、自强不息的模样；通过话剧《杨石先》片段的展演，同学们用心呈现了杨石先老校长一生鞠躬尽瘁、奉献祖国的赤子之心；话剧《破晓》在舞台上如画卷般呈现，带领师生们重温抗日战争的革命岁月，展现出红色信仰的伟大力量；同学们还创新改编了影视剧《觉醒年代》片段，再现了百年前的社会民情和人生百态，一段波澜壮阔的如歌岁月，一幅幅人物群像被生动演绎，饱含深情，直击人心。\n演出结束后，王兰对同学们的话剧表演给予了充分的肯定。她说，本次话剧节的前期筹备与现场展演，一方面加深了同学们对党史的理解，另一方面也加深了大家对于生物学科的认识，希望同学们能够积极向革命先辈学习，在日常生活中发扬顽强拼搏、永不服输的精神。\n此次“话谈百年 剧演生科”话剧节传承经典作品，创新表现形式，是生科院强化学生理想信念教育的重要举措，让同学们在话剧展演、活动筹备的过程中进一步深化了对党史、校史、生物学科发展史的了解与认识，积极践行青年人的责任与担当。今后，学院将继续拓展教育形式，丰富教育载体，引导学生树立科研报国志向，培养公能兼济的南开学子。",
  "content_length": 869,
  "snapshot_hash": "8a650232b933d31bb0024641b22089cf",
  "attachments": [],
  "crawl_time": "2025-05-29T05:04:40.445931",
  "list_page_url": "https://news.nankai.edu.cn/dcxy/system/count//0005000/000000000000/000/000/c0005000000000000000_000000492.shtml"
}