{
  "id": 1910,
  "title": "化学学院第四期业余党校开学",
  "url": "http://news.nankai.edu.cn/dcxy/system/2010/05/05/000030265.shtml",
  "date": "2010-04-05",
  "source": "来源： 南开新闻网",
  "content": "南开新闻网讯(通讯员 石 瑶)日前，南开大学化学学院第四期学生业余党校开学典礼成功举行。化学学院党委书记杨光明教授、学生工作办公室主任许萌及本期业余党校七十余名学员参加了开学典礼。\n典礼首先由学生工作办公室主任、业余党校校长许萌老师介绍化学学院业余党校基本情况。她告诉各位学员，为让化学学院新生党员和预备党员增强自身党性修养，使广大入党积极分子和入党申请人加深对党的基本知识和基本理论的理解，树立共产主义理想和建设中国特色社会主义的信念，增强爱国热情和爱党、爱校的优良传统；同时丰富学生们的课余文化生活，培养团体精神，树立为党、为社会、为人民服务、求真务实的理想信念，化学学院针对大一年级新生创办了学生业余党校。本学期已经是业余党校第四期，目前已经成为化学学院学生思想政治教育工作的日常工作和品牌活动。\n随后，杨光明发表讲话，他对第四期业余党校的成立表示了热烈的祝贺，肯定了前三期业余党校的成果，预祝本期业余党校取得更大成功。他指出，党和国家奋斗目标的实现，靠的是忠诚党的事业的党员来贯彻执行。党员同志们要积极奋斗，也要抓住机遇。他勉励学员们要做好充分的准备，增强自身素质的培养。院业余党校为大家提供这样一个平台，希望大家通过学习提高认识，展示能力，更快更好的抓住机遇，实现党和国家及个人的奋斗目标。\n开学典礼之后，随即进行本期业余党校第一讲，由杨光明主讲“发展党员流程”。杨光明用文图详细的演示资料向大家讲授了化学学院党员发展流程，广大学员认真听讲并做笔记。演讲之后，杨光明同广大学员进行了深入的交流，并对同学们关心的问题一一作了解答。广大学员纷纷表示这次讲座非常有意义，党员胡逸凡表示：“业余党校的学习对于党支部的同志来说，认真掌握发展流程就是对积极要求入党的同学一种负责；而那些积极要求入党的同学也从此次讲座中受益匪浅。”\n开学典礼当天也是学员吴奕龙的生日。业余党校为他准备了一本《中国共产党章程》作为特别的生日礼物，希望他努力学习党的理论知识，加强自身修养，努力争取早日成为中国共产党的一员。",
  "content_length": 850,
  "snapshot_hash": "195aa71989b06f66f4746c7f303a8721",
  "attachments": [],
  "crawl_time": "2025-05-29T01:16:56.856229",
  "list_page_url": "https://news.nankai.edu.cn/dcxy/system/count//0005000/000000000000/000/000/c0005000000000000000_000000063.shtml"
}