{
  "id": 9162,
  "title": "“香溢于心 心溢于思”哲学文化周电影展播拉开帷幕",
  "url": "http://news.nankai.edu.cn/dcxy/system/2016/11/17/000305975.shtml",
  "date": "2016-11-18",
  "source": "来源： 南开新闻网",
  "content": "南开新闻网讯(通讯员 张蔚曦)11月12日，第十二届哲学文化周“香溢于心，心溢于思”影展活动在津南校区图书馆放映厅拉开帷幕。本次放映的影片是《超体》，一部由法国导演吕克·贝松执导、好莱坞知名女影星斯嘉丽·约翰逊主演的科幻动作片。哲学院贾江鸿教授应邀担任影展的点评嘉宾。\n在电影播放之前，贾江鸿从法国哲学方向阐释了对于电影和哲学关系的理解。他说，法国超现实主义的电影拍摄艺术其实来源于弗洛伊德的精神分析心理学和萨特的存在主义理论。这些影片无不细腻、感性，而且它们讨论着人与社会的关系。电影《超体》哲学命题就是：什么是生命的意义？用什么来证明我们的存在？我们到底为何而活着？\n同学们纷纷表示，通过观看这样一部影片，可以从中思考哲学命题，感受西方哲学与电影艺术的巧妙融合。",
  "content_length": 333,
  "snapshot_hash": "5eb6313ff2f054230dec9b1f2aa465b3",
  "attachments": [],
  "crawl_time": "2025-05-29T03:34:44.178344",
  "list_page_url": "https://news.nankai.edu.cn/dcxy/system/count//0005000/000000000000/000/000/c0005000000000000000_000000303.shtml"
}