{
  "id": 2985,
  "title": "周恩来政府管理学院研究生持续关注两会动态",
  "url": "http://news.nankai.edu.cn/dcxy/system/2011/03/07/000037344.shtml",
  "date": "2011-03-07",
  "source": "来源： 南开新闻网",
  "content": "南开新闻网讯(通讯员 东俊艳 高阳)“两会”之际，周恩来政府管理学院举办了“国策论坛”系列活动，旨在依托学科优势，引导广大青年学生关注国家、服务社会，激发其参政议政的热情。论坛上，同学们热议时政、建言献策；论坛外，同学们持续关注“两会”动态，聚焦政府工作报告。\n3月5日，第十一届全国人民代表大会第四次会议开幕。对于政府工作报告，外交学专业研究生狄英娜同学注意到温总理专门提出“十一五期间一些群众反映强烈的问题没有根本解决”，主要是：优质教育、医疗资源总量不足、分布不均；物价上涨压力加大，部分城市房价涨幅过高；违法征地拆迁等引发的社会矛盾增多；食品安全问题比较突出；一些领域腐败现象严重。狄英娜说这表明中央政府对于十一五期间国民经济社会发展的总结是客观全面的，政府报告的内容不只是总结成绩，而是直接面对仍存在的问题，对于全面做好十二五规划，反映民生问题，有着更加重要的意义。\n温家宝总理在政府工作报告中对十一五期间的国民经济做了全面总结。他指出，面对国际金融危机冲击，实施两年新增4万亿元投资计划，保障性安居工程、农村民生工程和社会事业投资占43.7%。彻底取消农业税和各种收费，每年减轻农民负担超过1335亿元。对此，家在山东农村的常晓升同学表示有着切身的感受，他说，过去的五年里，农村发生了巨大变化，农村经济发展迅速，农民没有了农业税的负担，还能拿到种粮补贴，种粮积极性得到提高；同时，在农村社会保障方面，农民也有了医疗保险、养老保险，农村社会基础设施建设得到极大改善，农民生活水平有了明显提高。\n更加让即将毕业留在天津工作的同学们激动的是，温总理再一次提到了要充分发挥天津滨海新区在改革开放中的先行先试作用，政治学理论专业研究生杨广伟同学表示，这更加说明天津和滨海新区的发展会更加迅速，也坚定了我留在天津，为天津发展，为滨海新区发展做出一份贡献的决心和信心。“留在天津，大有可为！”\n同学们通过电视或网络认真听取了温总理的政府工作报告，每条政策的落实和筹划，他们都能联系自己的所见所感，交流讨论。对于今年两会代表关注的一些热点问题，我院同学们也发表了自己的意见。\n今年即将毕业的同学关注的一个突出问题是个税起征点上调政策，这项有可能在今年两会期间获得通过的改革措施，对于即将踏上工作岗位的毕业生来讲意义重大，是关系到同学们切身利益的问题。行政管理专业研究生蒋丹荣说：今年夏天，我们就要开始自己的第一份工作，作为一个刚刚开始工作的大学生来讲，个税起征点的高低势必会影响到个人最终收入所得。同时，从专业角度分析，一方面，工资薪金所得减除费用标准的提高，降低了中低阶层赋税负担，等于变相提高了百姓的收入；另一方面，也是不断缩小收入分配差距、形成公平合理的国民收入分配格局的重要环节。这是政府传递出今后将更加关注民生，让发展成果更好惠及全民的信号。\n两会代表提出的救助流浪儿童的话题，令高翔同学激动万分。她说每次在大街上、地铁上，甚至学校里看到流浪乞讨的儿童，都会觉得很可怜，都会给他们钱，但是之后又会担心这些孩子是不是被人利用的。但是毕竟个人能力有限，没有办法真正的帮到这些孩子，现在两会代表开始关注这件事情，她非常支持，真希望能够形成相关立法案，通过各方面的努力，让他们和正常孩子一样拥有灿烂的明天。\n前些天温总理与网民的交流中，首先回答了关于幸福的问题，总理说，幸福就是让人们生活得舒心、安心、放心，对未来有信心。对于毕宇飞和她的同学们来讲，现在以及未来的幸福是切切实实的，那就是毕业找到一份满意的工作，然后和全体国民的愿望一样“学有所教、劳有所得、病有所医、老有所养、住有所居”，有希望，有尊严的生活。",
  "content_length": 1505,
  "snapshot_hash": "77ce1c3ebfce431c171e704e51617e3a",
  "attachments": [],
  "crawl_time": "2025-05-29T01:37:36.357635",
  "list_page_url": "https://news.nankai.edu.cn/dcxy/system/count//0005000/000000000000/000/000/c0005000000000000000_000000099.shtml"
}