{
  "id": 6565,
  "title": "【活力南开】跑步也能做公益 南开学子领你用运动献爱心",
  "url": "http://news.nankai.edu.cn/dcxy/system/2014/04/18/000177114.shtml",
  "date": "2014-04-18",
  "source": "来源： 南开新闻网",
  "content": "南开新闻网讯(实习记者 聂文斐 摄影 朱博晨)昨日，南开大学2012级电子科学与技术专业的李旭东一大早就爬出温暖的被窝，在7点准时到达操场，那里已经聚集了60余名师生，大家都是响应“公益晨跑”的微信动员前来的。五分钟的热身运动后，所有人都整齐的排成队伍，开启他们的集体晨跑之旅，并有专人记录每人的跑步里程。“很久没有早睡早起了，运动之后感觉神清气爽，上课也精力十足。”李旭东说，“我还领到了爱心卡片，一想到自己多跑几圈就能给贫困地区的小学生多捐献一件学习用品，每天起床都更有动力了。”\n像李旭东这样的同学有很多，他们每天呆的最多的地方就是教室、实验室和寝室，接触的也是书本、实验器材和电脑屏幕，时常会有人抱怨腰酸背痛、眼睛疲劳，又没有锻炼的动力，身体处于亚健康状态。看到同学们的这种状况，南开大学电子信息与光学工程学院老师贺文霞想到了用公益带动运动的方法。“每人晨跑累计里程达到2000米后，南开大学对口支援的甘肃省平凉市庄浪县贫困小学生将收到一本写有南开学子寄语的全新字典；累计里程到8000米后，庄浪地区小学生将收到一个装有学习用品的爱心书包。每位活动参与者都可以获得一张爱心明信片，我们会负责将同学们的鼓励和祝福寄给远方的孩子们。”贺文霞说，“此法既可以让大家‘走下网络，走出宿舍，走向操场’，强健体魄，养成良好的生活习惯，又可以为贫困小学献爱心，帮助大学生履行公益责任，可谓一举两得。”\n据了解，公益晨跑活动由南开大学学工部、团委主办，电子信息与光学工程学院承办，得到了近百名师生的关注与参与，将持续至4月30日。届时，学校还会开展图书募集活动，鼓励同学将不再使用的课外书籍捐赠出来。今年暑假，南开大学暑期社会实践队将会携带公益晨跑捐赠的物资与募得图书前往庄浪地区，并在当地建立南开图书屋。",
  "content_length": 749,
  "snapshot_hash": "a2ec1fea1131e6664c2a28547b84d982",
  "attachments": [],
  "crawl_time": "2025-05-29T02:45:15.187166",
  "list_page_url": "https://news.nankai.edu.cn/dcxy/system/count//0005000/000000000000/000/000/c0005000000000000000_000000218.shtml"
}