{
  "id": 10966,
  "title": "“大冰的小屋 百城百校音乐会”南开站完美收官",
  "url": "http://news.nankai.edu.cn/dcxy/system/2018/11/18/000419097.shtml",
  "date": "2018-11-18",
  "source": "来源： 南开新闻网",
  "content": "南开新闻网讯(学生记者 张宇 张晓丽 摄影记者 郑晴予 张纪茜)2018年11月16日晚，“大冰的小屋•百城百校音乐会”在南开大学商学院报告厅举行。本次音乐会的嘉宾为大冰的小屋•厦门分舵成员王继阳和谣牙子。\n首先登场的王继阳用幽默风趣点燃了现场气氛。他跟大家分享了大梦在北极的求婚故事，“大冰的小屋”的由来，以及《送你一只喵》这篇文章的暖心背景。\n身为天津人的王继阳，他的演唱带有鲜明的地域风格。《探清水河》有浓郁的天津风味；用京剧唱腔演绎的《青春修炼手册》将现场气氛带向高潮，展现了他的唱腔功底；在甘肃支教时为当地学校写的校歌《大山里的孩子》，更是让现场观众情不自禁地打开手机灯光，挥手为他助力。\n谣牙子登场后为大家演唱了《年华的记忆》《繁星》等五首歌曲。《陪我到可可西里去看海》是音乐会的最后一首歌，现场观众齐唱，音乐会在歌声、掌声中缓缓落下帷幕。\n此次音乐会上，歌手们分享了自己的成长经历和人生故事，鼓励了同学们要勇敢追逐人生梦想，去探索生活的更多可能。同时也让同学们有机会欣赏民谣演唱，丰富了同学们的文娱生活。2018级文学院本科生余星兰表示：“民谣除了有好听的旋律以外，最打动我的其实是民谣背后的故事。很开心今晚的音乐会让我不仅能现场听到民谣，还有机会了解歌曲以外的更多故事。”\n“大冰的小屋•百城百校音乐会”项目作为大冰对书迷的回馈，2015年至今已累计举办1000余场。此次南开站的活动由南开大学商学院学生会文艺部承办。",
  "content_length": 617,
  "snapshot_hash": "13a3e551fe3dbc4bd9903fb32c6fe586",
  "attachments": [],
  "crawl_time": "2025-05-29T04:08:18.032473",
  "list_page_url": "https://news.nankai.edu.cn/dcxy/system/count//0005000/000000000000/000/000/c0005000000000000000_000000365.shtml"
}