{
  "id": 13373,
  "title": "计算机学院和网络空间安全学院学子积极投身抗洪救灾志愿服务",
  "url": "http://news.nankai.edu.cn/dcxy/system/2021/08/04/030047502.shtml",
  "date": "2021-08-05",
  "source": "来源：",
  "content": "南开新闻网讯（通讯员 薛颖）近日，河南郑州、新乡、鹤壁等地普降特大暴雨，面对灾情，我校计算机学院和网络空间安全学院学生主动请缨成为抗洪救灾志愿者，以实际行动践行新时代青年的使命与担当，彰显爱国报国的青春风采。\n党员冲锋在前 尽己所能排险\n作为一名中共党员，暴雨恰逢生日的2018级博士研究生金宸在面对新乡市出现漫堤险情的牧野湖边，与民众一起自制沙袋，在倒灌严重地区垒沙袋避险。待部队赶到救险后，他又作为社区志愿者到受灾严重的村子发放物资。金宸说，今年的生日与家乡父老一起以风为号、以雨为旗，奔走在抗洪救灾志愿服务中，是最难忘的一次生日。\n参与专业救援 全力服务一线\n2020级本科生苗发生主动报名加入专业救援队，前往一线抗洪救灾。身在新乡市的他与专业人员在决口处搭建帐篷、装沙袋、搬沙袋，协助传达需求及提供后备物资、一日三餐等工作。一线工作结束后，他还协助村子清理积累多日已发出刺鼻气味的垃圾，胶靴保护下他们的脚依然被水浸泡到臃肿，甚至起了红疹。他说，感受到苦与累的同时，更重要的是在奉献与付出中收获了幸福感与满足感。\n支援后勤服务 发挥大学生优势\n2020级本科生王佩婕身在郑州市，她和志愿者在布满水和淤泥的地铁站内清理废料、垃圾、淤泥和积水，有些还未修复电力的地铁站甚至需要打着手电筒工作。身在周口市的2020级本科生赵琼主要负责安顿撤离到后方的居民，秉承“天天来，事事做”的原则，她每天引领居民领取饭票，指导高三学生课业疑问，关照老年人特殊需求、协助搬运大量物资。\n线上协同救灾 提升救援效率\n身在天津的2019级本科生刘成第一时间报名成为卓明救援组织的线上志愿者，电话联系安置点负责人对郑州、新乡等地部分安置点的需求信息进行搜集和汇总，按照紧迫程度分级整理后发布到卓明村需求信息平台，极大提升了后续资源的高效率对接。\n面对突如其来的灾害，计算机学院和网络空间安全学院学生闻“汛”而动，用热血与情怀守护祖国，在志愿服务中锻炼能力，在防汛救灾中绽放青春，彰显南开学子风采。",
  "content_length": 838,
  "snapshot_hash": "5c0a1a7f85bfbdd4dbb2cabbb4f8d912",
  "attachments": [],
  "crawl_time": "2025-05-29T04:44:42.704544",
  "list_page_url": "https://news.nankai.edu.cn/dcxy/system/count//0005000/000000000000/000/000/c0005000000000000000_000000445.shtml"
}