{
  "id": 2817,
  "title": "南开大学志愿者交流会举行",
  "url": "http://news.nankai.edu.cn/dcxy/system/2010/12/06/000036051.shtml",
  "date": "2010-12-06",
  "source": "来源： 南开新闻网",
  "content": "南开新闻网讯(学生记者 翟志超 武东翔 摄影 施旺)12月5日晚，由南开大学青年志愿服务与社会实践中心主办的“南大奥运会、世博会、达沃斯、亚运会志愿者交流会”在新学生活动中心举行，我校青年志愿服务与社会实践中心主要负责人和全校各院系志愿者代表一起参加了活动。\n经验交流会在《青年志愿者之歌》中拉开了帷幕。随后，参加过2008年北京奥运会、2010年上海世博会、广州亚运会和天津夏季达沃斯论坛的志愿者们向到场代表介绍了他们的志愿者心得。\n曾经休学一年在陕西支教的历史学院07级硕士严少华认为，志愿者可以分为两种，一种是有头衔的，一种是没有头衔的。有头衔的志愿者是大家平时关注的，名头响亮的，比如“奥运会志愿者”、“世博志愿者”。但头衔并不能说明什么，重要的是为大家服务，哪怕只是随手关灯这样的小事，只要是付出了，就是光荣的。而正因为有了众多不求头衔的志愿者们，社会才变得更加和谐。其他志愿者也纷纷表示，作为志愿者，重要的是从奉献中收获了什么，思考了什么，有什么能够为将来的志愿活动服务，这才是参加志愿活动的真谛。\n经验交流会在轻松愉快的氛围中展开，此外，会中还穿插了知识问答环节和自由提问环节，现场观众的积极参与与巧妙提问，将现场的气氛带向高潮。\n我校青志协分管培训部的副主任，信息技术科学学院2009级本科生刘成成说，参加此次交流大会的志愿者不仅开阔了眼界，丰富了知识，更获得了一种精神和智慧的熏陶，甘于奉献、吃苦耐劳、责任意识……希望此次心得交流会能更加激发同学们参与志愿活动的热情，让更多人参与到志愿活动中，让社会变得更加美好。",
  "content_length": 666,
  "snapshot_hash": "6008a1e102698c40f459804a9cebe080",
  "attachments": [],
  "crawl_time": "2025-05-29T01:34:34.503792",
  "list_page_url": "https://news.nankai.edu.cn/dcxy/system/count//0005000/000000000000/000/000/c0005000000000000000_000000094.shtml"
}