{
  "id": 3081,
  "title": "法学院召开社团负责人工作交流会",
  "url": "http://news.nankai.edu.cn/dcxy/system/2011/03/21/000037718.shtml",
  "date": "2011-03-21",
  "source": "来源： 南开新闻网",
  "content": "南开新闻网讯(通讯员 张春玲)近日，法学院针对挂靠在学院团委的各个社团召开了社团负责人工作交流会。学院负责社团工作的老师，团委学生负责人，法律援助协会、笛箫协会、跑步协会和JESSUP辩论协会的负责人参加了本次工作交流会。\n会上，各社团负责人针对2010至2011第一学年度的社团的发展情况、活动开展情况以及组织建设情况进行了梳理和总结，指出了上学期各自社团工作的优点和不足之处，同时汇报了本学期的社团工作计划和重点工作安排。各社团负责人针对社团工作中的重点与难点问题互相交流经验，取长补短。\n负责社团工作的老师听取了各个社团负责人的工作汇报，针对各个社团的工作情况进行了有针对性的指导，同时在会上通报了校团委关于学生社团管理工作的各项规章制度，强调了各社团开展活动的注意事项，提出了社团工作的工作规范与工作要求，并对社团今后的发展建设问题做了重要提示，对各个社团提出了以下几点希望：一、规范社团管理制度，遵守学校团委关于社团管理的各项规章制度，将宣传、财务、会议、总结等工作做到实处；二、加强社团的建设与发展，发挥社团成员的能动性，积极开展创新性的品牌活动，争创品牌社团；三、增强社团活动开展过程中的安全防范意识与安全保障措施，保障各项活动积极健康的开展。\n会后，各社团负责人纷纷表示通过此次交流会收获良多，要在今后的工作中加强各社团之间的联系和沟通，互相借鉴，加强合作，同时表示要在着力做好本社团的各项基本工作的基础上大力开展社团特色活动、品牌活动，加强社团的发展与建设。",
  "content_length": 638,
  "snapshot_hash": "40482c1415dbaa4b67d905ecd608cd38",
  "attachments": [],
  "crawl_time": "2025-05-29T01:39:46.783550",
  "list_page_url": "https://news.nankai.edu.cn/dcxy/system/count//0005000/000000000000/000/000/c0005000000000000000_000000101.shtml"
}