{
  "id": 1407,
  "title": "寸草济困助学金受助学生座谈“我的大学我的梦”",
  "url": "http://news.nankai.edu.cn/dcxy/system/2009/05/19/000023802.shtml",
  "date": "2009-05-19",
  "source": "来源： 南开新闻网",
  "content": "南开新闻网讯(通讯员 任子雄)5月15日，南开大学举办了以“我的大学我的梦”为主题的“寸草济困助学金”受助学生座谈会。座谈会旨在提高我校“寸草济困助学金”受助学生的综合素质，引导他们更好地规划人生，高效学习、充实生活，使每一名受助学子都能成长成才。“寸草济困助学金”工作负责人秦惠玲女士出席会议。\n会上，学生资助管理中心刘唯真老师首先介绍了此次座谈会的主题、举办目的和具体安排。并为使同学们彼此熟悉，活跃座谈会气氛，她要求每一位同学用最简短的语言把自己介绍给大家。接着，她从“你期望中的大学是什么样的”、“如何度过你的大学”、“你的未来在那里”3个方面对座谈会主题做了详细阐释，并鼓励同学们踊跃畅谈自己的想法。\n与会同学围绕主题畅所欲言。有同学表示，南开大学不仅有像周恩来总理这样的杰出校友，还有浓厚的学术氛围和自由的学习环境。这些都是自己选择南开的动力所在。有同学则以《平凡的世界》中主人翁对改变自己命运的不懈努力、对追求自己理想的矢志不移的人生经历为例，来畅谈自己的大学梦。还有同学表示，金融危机对就业的影响是我们无法改变的，但我们可以努力改变自己，全面提高自己的综合素质，增强自己在未来职场上的竞争力。不管在大学期间，还是在其他任何时候，都能做到不消沉、永远保持积极健康向上的心态，这是成功必不可少的。\n秦惠玲女士认真听取了各位同学的发言，对同学们能够正确的认识自己、客观地评价周围的人和事、并对自己的未来做了详尽的规划给予了充分的肯定。同时，她与大家交流了她对“我的大学我的梦”这一主题的想法。她认为，大学期间，不仅要学好各种专业知识，还要注重培养自己的品质、意志和修养。拥有高尚的品质、坚强的意志和良好的修养将使同学们一生受益。她指出，个人的理想和时代的大背景是密不可分的，要实现自己的理想，不仅要扎扎实实的努力工作，也要有与时俱进的思想意识。\n最后，学生资助管理中心李亮老师对此次座谈会的成功举办表示祝贺，并对同学们提出三点希望。一是希望同学们要懂得感谢国家、社会和“寸草济困助学金”。二是要感谢“寸草济困助学金”工作负责人秦惠玲女士。她在工作之余，担负起了“寸草济困助学金”的日常管理工作，并对每一位受资助同学的基本情况一一作了了解，工作非常细致，这正是体现了她对同学们的无私关怀。三是希望同学们怀着这种感激之情，刻苦学习、努力工作，为国家和社会做出自己的贡献。",
  "content_length": 988,
  "snapshot_hash": "a0874fbb54b74ef632f68ebbb3f8cde1",
  "attachments": [],
  "crawl_time": "2025-05-29T01:06:49.055304",
  "list_page_url": "https://news.nankai.edu.cn/dcxy/system/count//0005000/000000000000/000/000/c0005000000000000000_000000048.shtml"
}