{
  "id": 9960,
  "title": "电光学院举办2017级新生迎新晚会",
  "url": "http://news.nankai.edu.cn/dcxy/system/2017/09/28/000347761.shtml",
  "date": "2017-09-28",
  "source": "来源： 南开新闻网",
  "content": "南开新闻网讯(通讯员 朱博晨 李潆溪)近日，电子信息与光学工程学院在大通学生活动中心音乐厅举办了以“秉承公能日新，牢树四个自信，勇担时代使命”为主题的2017级新生迎新晚会，电光学院党委副书记、副院长贺文霞出席了本次迎新晚会。电光学院全体2017级新生及学生家长代表参与了本次晚会。\n晚会在一曲悠扬的钢琴独奏《梦中的婚礼》中正式开始。歌曲串烧节目，同学们将戏曲、流行歌曲、吉他弹唱、二胡演奏等融合在一起。高年级学生特别准备了重新编曲的歌曲《一个人》，爱乐音乐协会则将电子设计与音乐表达结合，展现理工科学生的文艺清华。\n语言类节目中，相声《财从天降》讲述了普通人突变富二代的奇遇，幽默自然惹人发笑同时发人深省；由新生自导自演的小品《南开“水群”广播电台》则是结合当下新生在网络聊天的种种表现，通过小品包袱、表情包运用等表达了同学们对于网络世界的思考；诗朗诵《将进酒》则表现了传统文学的独特美感。\n舞蹈类节目中，Fashion街舞社通过酷炫的舞姿，将现场气氛点燃；舞蹈《告白气球》表现了大学爱情的单纯美好；辅导员老师与高年级学生共同带来的舞蹈表演《失恋阵线联盟》更是把气氛推向了最高潮。\n在一曲合唱《相亲相爱》中，本次晚会圆满结束。许多新生家长通过观看网络直播，参与到本次晚会中来。据悉，本次迎新晚会是17级新生入学活动的收官之作，学院旨在通过一场极具美感的视听盛宴，让新生们展示自我才艺，增进彼此间的感情，更快地融入学院、适应大学生活，并激励新生秉承公能日新的南开精神，勇于承担为国效力的时代使命。",
  "content_length": 648,
  "snapshot_hash": "96144facfac84564d1e0d7a8d8a2220a",
  "attachments": [],
  "crawl_time": "2025-05-29T03:49:47.263144",
  "list_page_url": "https://news.nankai.edu.cn/dcxy/system/count//0005000/000000000000/000/000/c0005000000000000000_000000330.shtml"
}