{
  "id": 14151,
  "title": "【学习贯彻二十大】文学院文荟团校举行专题理论学习暨微团课大赛",
  "url": "http://news.nankai.edu.cn/dcxy/system/2022/11/23/030053784.shtml",
  "date": "2022-11-24",
  "source": "来源： 南开大学新闻网",
  "content": "南开新闻网讯（通讯员 高毓坤 韩国瑞） 为深入学习宣传贯彻党的二十大精神，提升团员青年的思想政治素质，近日，文学院文荟团校举行了“青春献礼二十大，强国有我新征程”系列学习活动，文学院党委副书记李广欣、各年级辅导员和团校全体学员参加学习。\n在专题理论学习会上，文荟团校邀请文学院2020级本科生党支部和文学院“诗话中国”宣讲团做理论宣讲。2020级本科生党支部宣讲人方贝儿、胡晚晴分别从科技创新和青年责任的角度诠释了对党的二十大精神的理解。方贝儿通过一段视频资料展示了近十年来我国在科技领域取得的伟大成就，激励同学们坚定不移跟党走，积极学习先进科学知识，主动投身时代发展的大潮。胡晚晴以详实的事例向同学们展示了青年人对投身国家建设的自豪和对未来美好生活的期盼，她与全体团校成员共勉，牢记习近平总书记的殷殷嘱托，立志成为有理想、敢担当、能吃苦、肯奋斗的新时代好青年。\n文学院“诗话中国”宣讲团从文化传承的角度对党的二十大精神进行阐释。宣讲人李孜涵、刘兴悦指出，回望几千年来中国历史发展进程，中华优秀传统文化绵延不断，一直推动着社会的发展。铸就社会主义文化新辉煌，离不开对中华优秀传统文化的保护与传承。作为文学院的青年学子，传承中华优秀传统文化不仅是专业学习的基本要求，更是义不容辞的时代使命，同学们应充分利用学习资源，学好专业知识，做中华优秀传统文化的传承者和弘扬者。\n在微团课大赛上，文学院2022级本科新生团支部团学骨干同台竞技，围绕“深入学习宣传贯彻党的二十大精神”这一主题，以青年人的所学所思所悟，从不同角度宣讲党的二十大精神。有梳理近十年来国家发展的大事记，回望党带领人民砥砺奋进的非凡十年；有将学习党的二十大精神和学习习近平总书记视察南开大学时的重要讲话精神相结合，谈南开学子的奋斗目标；有从马克思《青年与职业选择时的考虑》一书入手，谈新时代青年的职业选择问题；有从“学团章、守纪律、强意识”入手，带领同学们重温团章，明确共青团员的行为规范……\n经过精彩的角逐和评委老师们的无记名投票，文学院2022级本科生设计二班团支部韩致远、窦晓潼获得本次微团课大赛的一等奖。大赛结束后，李广欣进行总结发言，他肯定了同学们对党的二十大精神的理解把握以及在比赛中所展现出的良好精神风貌，希望同学们在团校学习中不断汲取精神力量，以实际行动贯彻落实党的二十大精神。\n学习贯彻二十大，砥砺奋进新征程。文荟团校此次系列学习活动，注重以党建带团建，以团建促发展，通过领学观摩、同台宣讲的方式，调动了团员青年开展理论学习的主动性和积极性，也激发了新生团支部的活力，为新生团支部建设提供了有益经验。",
  "content_length": 1089,
  "snapshot_hash": "b7db91ff5621af0a49dc7443f8c354fe",
  "attachments": [],
  "crawl_time": "2025-05-29T04:56:12.447477",
  "list_page_url": "https://news.nankai.edu.cn/dcxy/system/count//0005000/000000000000/000/000/c0005000000000000000_000000471.shtml"
}