{
  "id": 7861,
  "title": "化学学院动员五四评优",
  "url": "http://news.nankai.edu.cn/dcxy/system/2015/10/29/000253255.shtml",
  "date": "2015-10-29",
  "source": "来源： 南开新闻网",
  "content": "南开新闻网讯(通讯员 贺家豪 姚慧)近日，化学学院五四评优动员会议举行。\n会上介绍了“五四评优”的举办目的、申报要求以及申报流程，三个参评团支部代表分享经验。",
  "content_length": 79,
  "snapshot_hash": "86cb419ac74820ac183b80d997abcb55",
  "attachments": [],
  "crawl_time": "2025-05-29T03:10:19.763353",
  "list_page_url": "https://news.nankai.edu.cn/dcxy/system/count//0005000/000000000000/000/000/c0005000000000000000_000000261.shtml"
}