{
  "id": 12790,
  "title": "计算机学院和网络空间安全学院开启“就业先锋特训营”",
  "url": "http://news.nankai.edu.cn/dcxy/system/2021/03/17/030044934.shtml",
  "date": "2021-03-17",
  "source": "来源： 南开大学新闻网",
  "content": "南开新闻网讯（通讯员 戚晓睿 谭彤彤）3月13日，计算机学院和网络空间安全学院举办“就业先锋特训营”第一期工作经验分享会，邀请到2017级计算机学院诸佳昕，2017级网络空间安全学院聂荣志、于洪霄三位优秀毕业生，面向全院本科生做主题为“就业实习经验分享”的分享，旨在通过学生榜样现身说法，帮助学生形成正确的择业观、就业观，提升学生就业竞争能力。\n分享会上，聂荣志做题为Offer: Your Production的分享，针对求职理念、简历制作两方面进行详细介绍；于洪霄从确立目标到复习准备，分享了自身的就业经历；诸佳昕着重分享了实习及笔试面试经验，建议同学们提早准备不局促，理智投递不盲从。他们还围绕同学们提出的有关就业实习等问题进行耐心解答，现场讨论热烈，气氛融洽。\n据悉，计算机学院和网络空间安全学院将以本次分享会为起点，打造“就业先锋特训营”品牌系列活动，持续关注学生提升就业竞争力，培育公能兼备的拔尖人才。",
  "content_length": 407,
  "snapshot_hash": "1c2d132e0a3a883d7a134c0d3944f70b",
  "attachments": [],
  "crawl_time": "2025-05-29T04:36:16.172199",
  "list_page_url": "https://news.nankai.edu.cn/dcxy/system/count//0005000/000000000000/000/000/c0005000000000000000_000000428.shtml"
}