{
  "id": 12867,
  "title": "材料学院开展寒假留校学生新春慰问系列活动",
  "url": "http://news.nankai.edu.cn/dcxy/system/2021/02/12/030044576.shtml",
  "date": "2021-02-12",
  "source": "来源： 南开大学新闻网",
  "content": "南开新闻网讯（通讯员 董悦）新春将至，寒假开启，大多数学子已踏上归程与家人团聚，然而或因受疫情影响、或利用假期完成科研攻关任务与创新创业项目，材料学院51名学子不能如期返乡。学院高度重视留校学生的身心健康和学习、生活需求，2月11日，农历除夕佳节之际，学院开展新春慰问系列活动，了解学生实际需求，并送上新春慰问礼品与祝福。\n灼灼暖心，明晰需求。2月11日上午，学院召开留校学生慰问座谈会，学院党委副书记兼副院长李刚参加会议，会议由本科生辅导员董悦主持。李刚向留校学生送去新春祝福并叮嘱同学们留校期间要注意安全，遵守疫情防控期间学校与学院的相关规定，同时邀请学生参加学院举办的各类新春文化活动，增长见闻的同时提升个人能力。会后，李刚与学院学生党支部留校支书、支委前往学院相关实验室进行安全自查自检，确保寒假春节期间校园实验安全稳定。\n殷殷期望，佳节礼庆。时值农历春节之际，学院为每位留校学子准备“新春慰问大礼包”，内含由学校提供的免费餐券、新春贺岁福袋以及学院准备的“旺材”礼包等，力求为留校学生在校生活做好强有力的支持和保障。\n奕奕风采，迎春送福。学院坚持“五育并举”育人理念，开展“学习传统文化，共庆传统佳节”迎新春系列校园文化活动，包括“巧手佳话添年味”迎春书法大赛、水饺制作比拼等年味十足的新春活动，以传统文化传递吉庆祥和，培养健康向上的审美情趣，以迎庆传统年节之契机培育学生家国情怀。\n据悉，材料学院还将继续深植中华传统文化根基，在满足疫情防控安全的前提下，针对留校学生开展丰富多样的迎新春校园文化活动，为身处异乡的学子提供别样温情，助力健康成长。",
  "content_length": 678,
  "snapshot_hash": "05ab3732ac9451970eeca85a13145885",
  "attachments": [],
  "crawl_time": "2025-05-29T04:37:07.762764",
  "list_page_url": "https://news.nankai.edu.cn/dcxy/system/count//0005000/000000000000/000/000/c0005000000000000000_000000427.shtml"
}