{
  "id": 2017,
  "title": "在职法律硕士举办防灾减灾日宣传活动",
  "url": "http://news.nankai.edu.cn/dcxy/system/2010/05/13/000030480.shtml",
  "date": "2010-05-13",
  "source": "来源： 南开新闻网",
  "content": "南开新闻网讯(通讯员 谢扬今)2010年5月12日是我国第二个防灾减灾日，我校2010级在职法律硕士研究生班举办活动宣传防灾减灾知识，并组织全班同学为灾区捐款奉献爱心。\n2010级在职法律硕士研究生班主要由来自天津市各级公、检、法系统的工作人员组成，在活动过程中，同学们结合专业知识，以《中华人民共和国防震减灾法》为切入点，通过制作宣传单、提供网络下载资源，现场解答问题等方式宣传防震减灾知识，并结合今年防灾减灾日的主题，宣传“社区减灾”的常识。\n2010级在职法律硕士张鑫磊同学说，全班同学都很珍惜到南开大学攻读在职学位的机会，在学好专业知识的同时，大家都希望能够积极参与到学校的各项活动中来，履行自已作为南开人的一份责任。\n活动过程中，2010级法律硕士研究生班全体同学还组织了为玉树震区捐款活动，所捐款项将通过学校有关部门转交灾区。\n据南开大学法律硕士教育中心主任张荣强介绍，在职法律硕士多年来一直关注着学校的发展并积极参加相关的活动，同学们纷纷表示，无论是在读期间还是毕业以后，大家都希望通过各种方式为学校的发展建设多做工作。",
  "content_length": 467,
  "snapshot_hash": "2859224adca70562dc36777d4aac2a21",
  "attachments": [],
  "crawl_time": "2025-05-29T01:18:38.963187",
  "list_page_url": "https://news.nankai.edu.cn/dcxy/system/count//0005000/000000000000/000/000/c0005000000000000000_000000068.shtml"
}