{
  "id": 8245,
  "title": "经济学院“院长杯”足球赛开赛",
  "url": "http://news.nankai.edu.cn/dcxy/system/2016/03/17/000273418.shtml",
  "date": "2016-03-17",
  "source": "来源： 南开新闻网",
  "content": "南开新闻网讯(通讯员 王钊)3月14日，经济学院“院长杯”足球赛正式拉开帷幕，作为经济学院的传统活动，本届足球赛同样吸引了众多经院学子的参与和关注。\n根据前期报名选拔情况，本届比赛共有来自涵盖本科各年级的六支球队参赛，在接下来的两周内于八里台校区体育场进行角逐。决赛将于3月23日举行。\n据介绍，经济学院“院长杯”足球赛的举办延续了经济学院的优秀传统，是繁荣校园的体育文化、加强学生的体育意识的重要载体之一，使学生可以在比赛中能够体会运动之乐、体育之美，同时可以增进同学间的真挚友谊，增强学院凝聚力，真正做到友谊第一，比赛第二，在运动中收获友谊、收获健康。",
  "content_length": 278,
  "snapshot_hash": "08b217817a3396ef8c6521c110022ef1",
  "attachments": [],
  "crawl_time": "2025-05-29T03:17:17.627804",
  "list_page_url": "https://news.nankai.edu.cn/dcxy/system/count//0005000/000000000000/000/000/c0005000000000000000_000000274.shtml"
}