{
  "id": 975,
  "title": "温情中秋 齐聚南开",
  "url": "http://news.nankai.edu.cn/dcxy/system/2008/09/13/000018495.shtml",
  "date": "2008-09-13",
  "source": "来源： 南开新闻网",
  "content": "南开新闻网讯（学生记者 张虹）9月13日，南开园又迎来了新一批客人，08级新生在中秋佳节来临之际齐聚南开园，共同享受各学院为他们送去的中秋祝福。\n志愿者服务——第一份中秋礼物\n各具特色的展台分布在体育馆旁，每个学院的志愿者穿着整齐的桔黄色志愿服，迎接新生的到来。他们大早起床甚至顾不上吃早餐就开始了接站、指导新生入住等工作。\n生物科学学院的小纳说：“去年入学时有志愿者帮助了我们，今年我们也要把帮助和服务送给学弟学妹。就当是送给他们的第一份中秋礼物吧。”\n在南开园的各个角落里这样一群可爱的志愿者，总是把帮助和方便留给各地的新生和家长，为他们在中秋前夕送去了一份份真心的祝福。\n各院温情满怀迎新生\n今年的迎新工作正值一年一度的中秋节，所以各大院系除了做好迎新的入学指导和学习指导等方面的工作外，更加推出了温情中秋的迎新活动和细节安排。\n物理学院的老师夏焕云告诉记者：“中秋了，我们学院为了让家长和学生都有宾至如家的感觉，在他们来之前就在宿舍的门上贴好了院里领导老师亲自写好的中秋祝福贺卡，把真诚的祝福通过语言带给他们。另外导师还会在入住事宜结束之后给他们送去月饼，让他们在天津的第一个中秋过得愉快。”\n在软件学院的展台前，记者采访到了负责新生入学工作的老师，她动情地说：“在中秋迎来新的南开人，这是令人难忘而感动的。我们给他们送去月饼和关怀，以表达我们软件人对新生的中秋祝福，希望他们能够在这个集体里感受中秋的温馨。”\n环境科学与工程学院的党委副书记郭呈才说：“学院除了做好安排入住和学前教育工作外，这次迎新还会针对家长和学生在外过中秋的情况，举行中秋新生入学座谈会和茶话会，以加强师生间、学生间的交流和沟通，并送去月饼和水果共享中秋之乐。”\n中秋祝福温暖灾区学子\n今年南大有27名来自四川、甘肃的灾区学生入学，为了让他们在南开园享受中秋的快乐，相关学院在尊重他们心理的前提下做出了细心的工作安排。\n从数学学院的党委副书记易勇军那里，记者了解到：数学学院有两名灾区学生入学，学院对他们给予了特殊的关注，在做好学习生活等工作的同时，能够让他们过好在南大的第一个中秋节。送月饼、送关怀、开交流会，这样的活动希望能给他们带去异乡的中秋祝福。\n文学院团委书记金鑫告诉记者，学院将会举行迎新晚会，并且在中秋之夜在迎水道校区举办新生素质拓展活动，并在讲评时间吃月饼座谈，让他们能够互相结识加强交流沟通。这其中有两名灾区的学生，我们学院希望在尊重灾区学子情感的基础上通过一系列的活动让他们充分感受这个大家庭的温暖。",
  "content_length": 1050,
  "snapshot_hash": "43a466502335cfb340f3603843aa1b97",
  "attachments": [],
  "crawl_time": "2025-05-29T00:58:42.063977",
  "list_page_url": "https://news.nankai.edu.cn/dcxy/system/count//0005000/000000000000/000/000/c0005000000000000000_000000032.shtml"
}