{
  "id": 7633,
  "title": "马列学院学生代表实地设计新校区学院大楼内部空间",
  "url": "http://news.nankai.edu.cn/dcxy/system/2015/06/05/000236943.shtml",
  "date": "2015-06-05",
  "source": "来源： 南开新闻网",
  "content": "南开新闻网讯(通讯员 陈永刚)今年9月份，学生将正式搬入新校区，教学楼内部设计一直是同学们关心关注的“大事”。同学们通过院领导接待日、网络讨论等方式提出了大量宝贵建议。近日，马克思主义教育学院组织班级、党团支部以及学生社团代表到新校区实地设计学院大楼内部空间。学院党委副书记、副院长马亚男及辅导员代表一同前往。\n实地参观过程中，学生代表们围绕着新校区学院大楼的内外建筑风格，结合自身需求，在现场提出了很多具有较高参考价值的意见和建议。大到“学生工作办公室内外装饰风格”“学院图书阅览室的阅读环境设计”“学生社团活动室的整体规划”“学生活动荣誉室的建设”“学术交流研讨场地的布局”，小到“个性化储物空间的选取”“报刊杂志展架的安放”以及“教室内活动桌椅的摆放形状”等，同学们均进行了热议。\n通过组织学生对学院大楼实地进行整体布局和细节设计，进一步明确了学院未来在新校区建设发展的思路：全力满足学生个性化成长需求，广泛搭建师生交流的平台。",
  "content_length": 417,
  "snapshot_hash": "e5677fcb771fc61f2be258239e99e275",
  "attachments": [],
  "crawl_time": "2025-05-29T03:05:51.268737",
  "list_page_url": "https://news.nankai.edu.cn/dcxy/system/count//0005000/000000000000/000/000/c0005000000000000000_000000254.shtml"
}