{
  "id": 1121,
  "title": "“我与改革开放共成长”纪念改革开放30年教育活动启动",
  "url": "http://news.nankai.edu.cn/dcxy/system/2008/11/06/000019907.shtml",
  "date": "2008-11-06",
  "source": "来源： 南开新闻网",
  "content": "南开新闻网讯(通讯员钟鸣)日前，学校团委全面启动了纪念改革开放三十周年大型主题教育活动，进一步引导团员青年了解改革开放的伟大历程，理解改革开放的重大意义，探索投身改革开放建设的有效途径，以知识技能优势服务改革开放事业。活动将通过报告会、专题讲座、演讲、辩论、图片展等形式，让同学们在亲身参与中受教育、拓视野、长才干，活动时间持续两个月。\n辩论表演引热潮\n10月26日晚，辩论与口才协会与21世纪青年学社的一场以改革开放为主题的辩论表演赛，掀起了一场在校园里讨论改革开放的热潮。这也标志着本次改革开放三十周年主题教育活动的正式启动。05级学生吴涵说：“这次主题教育活动虽然紧密结合改革开放的历史巨变，但活动形式丰富多样，辩论赛、主题论坛都是青年学生们感兴趣的关注点。无论是组织者还是参加者，都能在轻松的过程中体会到改革开放带来的巨大影响。”\n演讲大赛谱新篇\n“再过三十年”——纪念改革开放三十周年主题演讲大赛也是主题教育活动的重要一环，旨在回顾过去的基础上展望未来，号召广大团年青年积极参与并在讲述改革开放三十年国家的巨大发展变化中深刻理解改革开放的意义，畅想未来更加辉煌灿烂的发展蓝图，激励他们在建设祖国的伟大征程中奋勇前进。11月2日晚，军事教研室艾跃进教授为本次演讲大赛做了专题培训讲座，指导广大同学更好地运用演讲与口才优势诠释改革开放的鲜明主题。\n“寻找”图片展览记足迹\n以“寻找”为主题，纪念改革开放历程的图片展览也在紧锣密鼓的筹备中，发动广大同学共同寻找记录改革开放历程的老照片，或亲手拍摄体现改革开放成果的新照片，以引领大家在“寻找”的过程中见证改革开放三十年的发展变化。\n主题论坛感成就\n主题活动还将邀请专家学者、在改革开放浪潮中获得成功的人士和亲历改革开放的身边人，以专场报告会、座谈会等形式畅谈改革开放感受，分享改革开放带来的成果，在团员青年中引起纪念改革开放和积极投身改革开放建设的共鸣。\n院系活动添风采\n各院系团学组织也纷纷围绕主题、立足自身特色开展主题活动，在扩大教育活动覆盖面的同时，在团员青年中营造以回顾、学习、总结、思考等方式纪念改革开放三十周年的浓厚氛围。",
  "content_length": 894,
  "snapshot_hash": "128f1ad82c029a9f077ebec71b952403",
  "attachments": [],
  "crawl_time": "2025-05-29T01:01:04.137286",
  "list_page_url": "https://news.nankai.edu.cn/dcxy/system/count//0005000/000000000000/000/000/c0005000000000000000_000000037.shtml"
}