{
  "id": 2396,
  "title": "天津市第四期大学生骨干培训班于南开大学举行",
  "url": "http://news.nankai.edu.cn/dcxy/system/2010/09/20/000033504.shtml",
  "date": "2010-09-20",
  "source": "来源： 南开新闻网",
  "content": "南开新闻网讯(通讯员 朱津函)9月18日，天津市第四期大学生骨干培训班在南开大学举行，出席活动的有共青团天津市委员会副书记史庆伟、学校部部长许瑞，天津市各高校团委书记以及第四期天津市大学生骨干培训班的成员。\n朱光磊教授对培训班成员举行了讲座，朱光磊分析了现今的社会背景，并对大家提出了殷切的希望。朱光磊教授指出，当今中国，人们的政治意识还存在着一定程度的欠缺。公与私、是与非，在一部分人意识中还存在着混淆。朱光磊教授曾在学生时代有着丰富的学生工作经验，他劝导当今的青年干部，更应该端正态度，保持自身思想作风秉直，在今后的工作中切实为社会服务。\n随后，同学们分组进行自由讨论。各位成员各抒己见，表达了听取讲座之后的感想，更明确了自身今后的任务——作为学生骨干，更应在学生之间起到良好的引领与导向作用。最后，大家还讨论了培训班的后期活动，包括实践锻炼策划书的相关方案等。\n此次天津市大学生骨干培训班活动圆满结束，同学们的思想境界也有了很大程度的提高，大家一致表示在今后更加完善自己，引领广大天津市大学生共同进步。\n南开大学学生会负责了礼仪与志愿服务工作。",
  "content_length": 475,
  "snapshot_hash": "496aca9129005629a1be30c85a9e3467",
  "attachments": [],
  "crawl_time": "2025-05-29T01:26:35.085479",
  "list_page_url": "https://news.nankai.edu.cn/dcxy/system/count//0005000/000000000000/000/000/c0005000000000000000_000000079.shtml"
}