{
  "id": 11712,
  "title": "文学院举行第二十期团校开班仪式",
  "url": "http://news.nankai.edu.cn/dcxy/system/2019/10/31/030036158.shtml",
  "date": "2019-10-31",
  "source": "来源：",
  "content": "南开新闻网讯（通讯员 周冰洁 摄影 王桂林）近日，文学院第二十期团校开班仪式在范孙楼218会议室举行，学院团委副书记赵可欣主持会议，2019级本科生共青团员代表、理论研修中心全体成员参加会议。\n开班仪式在庄严的共青团团歌声中拉开序幕。赵可欣介绍了本期团校的规章制度、课程安排、考核要求等内容。本期团校面向文学院2019级全体本科生，将在10月至11月开展团校理论课、团校讲堂、微团课比赛、志愿服务、青年教师进支部、实践调研、风采展示周等多种形式的理论学习和实践活动，目的是培养青年团员的理论修养和实践能力。\n本期团校在讲授理论知识的同时，较之以往更加注重提高共青团员的创新意识，在实践调研成果的展示形式方面，除传统的论文、话剧、歌曲之外，还增加了微信推送和调研视频等新内容。此外，本期团校积极邀请青年教师参与团校活动，进一步加强了师生之间的互动交流，增强了团组织的凝聚力。",
  "content_length": 386,
  "snapshot_hash": "824d5c6f089c3ce6506165721e69a8c5",
  "attachments": [],
  "crawl_time": "2025-05-29T04:21:18.382509",
  "list_page_url": "https://news.nankai.edu.cn/dcxy/system/count//0005000/000000000000/000/000/c0005000000000000000_000000390.shtml"
}