{
  "id": 7550,
  "title": "经济学院行业大讲堂——普华永道进校园活动圆满成功",
  "url": "http://news.nankai.edu.cn/dcxy/system/2015/05/13/000233154.shtml",
  "date": "2015-05-13",
  "source": "来源： 南开新闻网",
  "content": "南开新闻网讯(通讯员 雷珍妮)5月11日晚，由南开大学经济学院主办、经济学院团委素质教育中心承办的“经济学院行业大讲堂——普华永道进校园主题活动”于经济学院高层一楼报告厅举行。活动邀请了普华永道中天会计事务所天津分所的高级审计经理杨曼女士担任主讲嘉宾，为同学们讲述关于“审计”的那些事儿。\n杨曼通过四个浅显易懂的案例引出审计的主要工作内容，包括审查客户账户、报告公司财务状况、评估控制的有效性和提供资本市场服务。杨曼以“累并快乐”为关键词，讲述审计师的职场生活，认为审计工作的经历不仅有助于提升专业知识，而且有助于增强时间管理的能力。提问环节将活动推向了高潮，同学们关注的问题主要集中于审计师在普华永道的职业发展路径，对求职者的硬件要求和普华永道工作氛围等，杨曼则对同学们所关注的问题一一做出了细致的回答。\n活动在同学们的热烈掌声中结束。有同学表示，本场经济学院行业大讲堂活动帮助自己初步了解了审计行业的工作特点和求职要求，对即将踏入职场的同学们很有帮助。杨曼则表示，希望本次行业大讲堂能帮助学生们在求职路上少些迷茫，尽早实现自己的职业理想。",
  "content_length": 471,
  "snapshot_hash": "669e2b7fd605de6e7aa39c387f01092f",
  "attachments": [],
  "crawl_time": "2025-05-29T03:04:31.277067",
  "list_page_url": "https://news.nankai.edu.cn/dcxy/system/count//0005000/000000000000/000/000/c0005000000000000000_000000251.shtml"
}