{
  "id": 2527,
  "title": "呼唤外星人——南开大学教授苏宜谈系外行星探测",
  "url": "http://news.nankai.edu.cn/dcxy/system/2010/10/28/000034584.shtml",
  "date": "2010-10-28",
  "source": "来源： 南开新闻网",
  "content": "南开新闻网讯(通讯员 陈李娜 李瑶)10月22日，由教务处、校团委主办，学生科技协会承办的2010年创新教育文化月系列活动首场讲座在学生活动中心举行，题目为“呼唤外星人——系外行星的探测”天文科普讲座。主讲人为中国天文学会理事、天津市天文学会理事长、南开大学教授苏宜。\n在两个半小时的讲座中，苏宜结合地外生命存在的科学依据，分析了地外文明探索的艰巨性，还重点为大家讲述了太阳系外行星探测的几种主要方法——视向速度法、凌星法和微引力透镜方法，介绍了人们自1995年探测到第一颗系外行星以来所取得的丰硕成果，并展望了未来十几年内系外行星探测的前进方向。\n最后，同学们纷纷提问，与苏宜共同探讨天文学的发展等问题。",
  "content_length": 303,
  "snapshot_hash": "034f661002efb58e97d06e50e34873b1",
  "attachments": [],
  "crawl_time": "2025-05-29T01:28:52.798115",
  "list_page_url": "https://news.nankai.edu.cn/dcxy/system/count//0005000/000000000000/000/000/c0005000000000000000_000000083.shtml"
}