{
  "id": 2448,
  "title": "南开大学第八届学生科技文化节开幕",
  "url": "http://news.nankai.edu.cn/dcxy/system/2010/10/22/000034381.shtml",
  "date": "2010-10-22",
  "source": "来源： 南开新闻网",
  "content": "南开新闻网讯(通讯员 马婷婷)10月21日，由南开大学教务处、校团委主办，学生科技协会承办的“2010南开大学创新文化教育月”系列活动之“第八届学生科技文化节”开幕式举行。\n本次开幕式包含科技展板展出、飞机模型表演、有奖科技游戏三部分。科技展板展出由一张张讲述着科技前沿成果的展板组成，其范围涉及广告创新、生活常识以及技术创新等多个方面，精彩的创意和奇妙的设计让同学们大开眼界、流连忘返。\n飞机模型表演展出了三架精致的飞机模型，它们均由同学们自制而成。三架“飞机”不断做出滑行、起飞、空中转弯、倒飞等高难度动作，引得周围观众连连惊叹。\n有奖科技游戏让现场的气氛达到了最高潮，从最基本的三阶魔方、七阶魔方到九连环，再到精彩的科技问答，同学们纷纷大显身手，充分展示了自身丰富的科技素养。\n科技改变生活，协作带来机遇。科技文化节开幕式随着飞机的起落、九连环的破解、魔方的复原而结束，而“创新教育文化月”才刚刚开始。参与活动的科协成员表示，本届科技文化节的后续活动将集聚趣味和专业，定会吸引更多南开科技爱好者的到来。",
  "content_length": 454,
  "snapshot_hash": "bb4679f9e9fcf2b652289ec152a37c73",
  "attachments": [],
  "crawl_time": "2025-05-29T01:27:37.817399",
  "list_page_url": "https://news.nankai.edu.cn/dcxy/system/count//0005000/000000000000/000/000/c0005000000000000000_000000082.shtml"
}